{"schemaVersion":{"minor":3,"patch":0,"major":0},"sections":[],"identifier":{"url":"doc:\/\/SwiftUsd\/documentation\/OpenUSD\/Swift\/Bool","interfaceLanguage":"swift"},"topicSections":[{"title":"Initializers","anchor":"Initializers","identifiers":["doc:\/\/SwiftUsd\/documentation\/OpenUSD\/Swift\/Bool\/init(_:)-115q0","doc:\/\/SwiftUsd\/documentation\/OpenUSD\/Swift\/Bool\/init(_:)-12f6s","doc:\/\/SwiftUsd\/documentation\/OpenUSD\/Swift\/Bool\/init(_:)-15ljn","doc:\/\/SwiftUsd\/documentation\/OpenUSD\/Swift\/Bool\/init(_:)-16jvq","doc:\/\/SwiftUsd\/documentation\/OpenUSD\/Swift\/Bool\/init(_:)-18la","doc:\/\/SwiftUsd\/documentation\/OpenUSD\/Swift\/Bool\/init(_:)-19r9m","doc:\/\/SwiftUsd\/documentation\/OpenUSD\/Swift\/Bool\/init(_:)-1c4q4","doc:\/\/SwiftUsd\/documentation\/OpenUSD\/Swift\/Bool\/init(_:)-1i5gv","doc:\/\/SwiftUsd\/documentation\/OpenUSD\/Swift\/Bool\/init(_:)-1luc0","doc:\/\/SwiftUsd\/documentation\/OpenUSD\/Swift\/Bool\/init(_:)-1mj2o","doc:\/\/SwiftUsd\/documentation\/OpenUSD\/Swift\/Bool\/init(_:)-1mmhr","doc:\/\/SwiftUsd\/documentation\/OpenUSD\/Swift\/Bool\/init(_:)-1owj5","doc:\/\/SwiftUsd\/documentation\/OpenUSD\/Swift\/Bool\/init(_:)-1qrd5","doc:\/\/SwiftUsd\/documentation\/OpenUSD\/Swift\/Bool\/init(_:)-1r04v","doc:\/\/SwiftUsd\/documentation\/OpenUSD\/Swift\/Bool\/init(_:)-1tb4n","doc:\/\/SwiftUsd\/documentation\/OpenUSD\/Swift\/Bool\/init(_:)-1thf8","doc:\/\/SwiftUsd\/documentation\/OpenUSD\/Swift\/Bool\/init(_:)-1vcgr","doc:\/\/SwiftUsd\/documentation\/OpenUSD\/Swift\/Bool\/init(_:)-1vx95","doc:\/\/SwiftUsd\/documentation\/OpenUSD\/Swift\/Bool\/init(_:)-1y5uh","doc:\/\/SwiftUsd\/documentation\/OpenUSD\/Swift\/Bool\/init(_:)-22foc","doc:\/\/SwiftUsd\/documentation\/OpenUSD\/Swift\/Bool\/init(_:)-27z53","doc:\/\/SwiftUsd\/documentation\/OpenUSD\/Swift\/Bool\/init(_:)-28oyy","doc:\/\/SwiftUsd\/documentation\/OpenUSD\/Swift\/Bool\/init(_:)-2azq4","doc:\/\/SwiftUsd\/documentation\/OpenUSD\/Swift\/Bool\/init(_:)-2e9j2","doc:\/\/SwiftUsd\/documentation\/OpenUSD\/Swift\/Bool\/init(_:)-2ganp","doc:\/\/SwiftUsd\/documentation\/OpenUSD\/Swift\/Bool\/init(_:)-2gm7u","doc:\/\/SwiftUsd\/documentation\/OpenUSD\/Swift\/Bool\/init(_:)-2go3b","doc:\/\/SwiftUsd\/documentation\/OpenUSD\/Swift\/Bool\/init(_:)-2hek2","doc:\/\/SwiftUsd\/documentation\/OpenUSD\/Swift\/Bool\/init(_:)-2ioqb","doc:\/\/SwiftUsd\/documentation\/OpenUSD\/Swift\/Bool\/init(_:)-2mlpg","doc:\/\/SwiftUsd\/documentation\/OpenUSD\/Swift\/Bool\/init(_:)-2npd1","doc:\/\/SwiftUsd\/documentation\/OpenUSD\/Swift\/Bool\/init(_:)-2sprp","doc:\/\/SwiftUsd\/documentation\/OpenUSD\/Swift\/Bool\/init(_:)-32k7q","doc:\/\/SwiftUsd\/documentation\/OpenUSD\/Swift\/Bool\/init(_:)-33e65","doc:\/\/SwiftUsd\/documentation\/OpenUSD\/Swift\/Bool\/init(_:)-39ozz","doc:\/\/SwiftUsd\/documentation\/OpenUSD\/Swift\/Bool\/init(_:)-3b5qw","doc:\/\/SwiftUsd\/documentation\/OpenUSD\/Swift\/Bool\/init(_:)-3bmqq","doc:\/\/SwiftUsd\/documentation\/OpenUSD\/Swift\/Bool\/init(_:)-3gvxw","doc:\/\/SwiftUsd\/documentation\/OpenUSD\/Swift\/Bool\/init(_:)-3igwk","doc:\/\/SwiftUsd\/documentation\/OpenUSD\/Swift\/Bool\/init(_:)-3kyk2","doc:\/\/SwiftUsd\/documentation\/OpenUSD\/Swift\/Bool\/init(_:)-3nlk2","doc:\/\/SwiftUsd\/documentation\/OpenUSD\/Swift\/Bool\/init(_:)-3o5k","doc:\/\/SwiftUsd\/documentation\/OpenUSD\/Swift\/Bool\/init(_:)-3qdpt","doc:\/\/SwiftUsd\/documentation\/OpenUSD\/Swift\/Bool\/init(_:)-3t28w","doc:\/\/SwiftUsd\/documentation\/OpenUSD\/Swift\/Bool\/init(_:)-3t2wb","doc:\/\/SwiftUsd\/documentation\/OpenUSD\/Swift\/Bool\/init(_:)-40c5m","doc:\/\/SwiftUsd\/documentation\/OpenUSD\/Swift\/Bool\/init(_:)-447kh","doc:\/\/SwiftUsd\/documentation\/OpenUSD\/Swift\/Bool\/init(_:)-47y4f","doc:\/\/SwiftUsd\/documentation\/OpenUSD\/Swift\/Bool\/init(_:)-4a2cx","doc:\/\/SwiftUsd\/documentation\/OpenUSD\/Swift\/Bool\/init(_:)-4bxp0","doc:\/\/SwiftUsd\/documentation\/OpenUSD\/Swift\/Bool\/init(_:)-4hsn3","doc:\/\/SwiftUsd\/documentation\/OpenUSD\/Swift\/Bool\/init(_:)-4kn15","doc:\/\/SwiftUsd\/documentation\/OpenUSD\/Swift\/Bool\/init(_:)-4kvqu","doc:\/\/SwiftUsd\/documentation\/OpenUSD\/Swift\/Bool\/init(_:)-4mfl7","doc:\/\/SwiftUsd\/documentation\/OpenUSD\/Swift\/Bool\/init(_:)-4n62a","doc:\/\/SwiftUsd\/documentation\/OpenUSD\/Swift\/Bool\/init(_:)-4o3dw","doc:\/\/SwiftUsd\/documentation\/OpenUSD\/Swift\/Bool\/init(_:)-4pu1o","doc:\/\/SwiftUsd\/documentation\/OpenUSD\/Swift\/Bool\/init(_:)-4u74q","doc:\/\/SwiftUsd\/documentation\/OpenUSD\/Swift\/Bool\/init(_:)-54qbf","doc:\/\/SwiftUsd\/documentation\/OpenUSD\/Swift\/Bool\/init(_:)-54yuh","doc:\/\/SwiftUsd\/documentation\/OpenUSD\/Swift\/Bool\/init(_:)-5785k","doc:\/\/SwiftUsd\/documentation\/OpenUSD\/Swift\/Bool\/init(_:)-57oub","doc:\/\/SwiftUsd\/documentation\/OpenUSD\/Swift\/Bool\/init(_:)-59grs","doc:\/\/SwiftUsd\/documentation\/OpenUSD\/Swift\/Bool\/init(_:)-5fp8","doc:\/\/SwiftUsd\/documentation\/OpenUSD\/Swift\/Bool\/init(_:)-5h9cb","doc:\/\/SwiftUsd\/documentation\/OpenUSD\/Swift\/Bool\/init(_:)-5jboq","doc:\/\/SwiftUsd\/documentation\/OpenUSD\/Swift\/Bool\/init(_:)-5ob92","doc:\/\/SwiftUsd\/documentation\/OpenUSD\/Swift\/Bool\/init(_:)-5oibg","doc:\/\/SwiftUsd\/documentation\/OpenUSD\/Swift\/Bool\/init(_:)-5pgft","doc:\/\/SwiftUsd\/documentation\/OpenUSD\/Swift\/Bool\/init(_:)-5q3cx","doc:\/\/SwiftUsd\/documentation\/OpenUSD\/Swift\/Bool\/init(_:)-5qdkk","doc:\/\/SwiftUsd\/documentation\/OpenUSD\/Swift\/Bool\/init(_:)-5rhln","doc:\/\/SwiftUsd\/documentation\/OpenUSD\/Swift\/Bool\/init(_:)-5t6d7","doc:\/\/SwiftUsd\/documentation\/OpenUSD\/Swift\/Bool\/init(_:)-63kny","doc:\/\/SwiftUsd\/documentation\/OpenUSD\/Swift\/Bool\/init(_:)-64tmj","doc:\/\/SwiftUsd\/documentation\/OpenUSD\/Swift\/Bool\/init(_:)-65z1v","doc:\/\/SwiftUsd\/documentation\/OpenUSD\/Swift\/Bool\/init(_:)-68s5g","doc:\/\/SwiftUsd\/documentation\/OpenUSD\/Swift\/Bool\/init(_:)-6azcc","doc:\/\/SwiftUsd\/documentation\/OpenUSD\/Swift\/Bool\/init(_:)-6b8vj","doc:\/\/SwiftUsd\/documentation\/OpenUSD\/Swift\/Bool\/init(_:)-6dl38","doc:\/\/SwiftUsd\/documentation\/OpenUSD\/Swift\/Bool\/init(_:)-6f2qs","doc:\/\/SwiftUsd\/documentation\/OpenUSD\/Swift\/Bool\/init(_:)-6m3s1","doc:\/\/SwiftUsd\/documentation\/OpenUSD\/Swift\/Bool\/init(_:)-6mx0i","doc:\/\/SwiftUsd\/documentation\/OpenUSD\/Swift\/Bool\/init(_:)-6pmx3","doc:\/\/SwiftUsd\/documentation\/OpenUSD\/Swift\/Bool\/init(_:)-6qnkg","doc:\/\/SwiftUsd\/documentation\/OpenUSD\/Swift\/Bool\/init(_:)-6t6an","doc:\/\/SwiftUsd\/documentation\/OpenUSD\/Swift\/Bool\/init(_:)-6v4k8","doc:\/\/SwiftUsd\/documentation\/OpenUSD\/Swift\/Bool\/init(_:)-6vhi3","doc:\/\/SwiftUsd\/documentation\/OpenUSD\/Swift\/Bool\/init(_:)-6xnyv","doc:\/\/SwiftUsd\/documentation\/OpenUSD\/Swift\/Bool\/init(_:)-77uad","doc:\/\/SwiftUsd\/documentation\/OpenUSD\/Swift\/Bool\/init(_:)-7ed54","doc:\/\/SwiftUsd\/documentation\/OpenUSD\/Swift\/Bool\/init(_:)-7f7t0","doc:\/\/SwiftUsd\/documentation\/OpenUSD\/Swift\/Bool\/init(_:)-7gy5c","doc:\/\/SwiftUsd\/documentation\/OpenUSD\/Swift\/Bool\/init(_:)-7itb6","doc:\/\/SwiftUsd\/documentation\/OpenUSD\/Swift\/Bool\/init(_:)-7lr0x","doc:\/\/SwiftUsd\/documentation\/OpenUSD\/Swift\/Bool\/init(_:)-7maed","doc:\/\/SwiftUsd\/documentation\/OpenUSD\/Swift\/Bool\/init(_:)-7ohk3","doc:\/\/SwiftUsd\/documentation\/OpenUSD\/Swift\/Bool\/init(_:)-7p9wz","doc:\/\/SwiftUsd\/documentation\/OpenUSD\/Swift\/Bool\/init(_:)-7tyzt","doc:\/\/SwiftUsd\/documentation\/OpenUSD\/Swift\/Bool\/init(_:)-7u766","doc:\/\/SwiftUsd\/documentation\/OpenUSD\/Swift\/Bool\/init(_:)-7wks3","doc:\/\/SwiftUsd\/documentation\/OpenUSD\/Swift\/Bool\/init(_:)-7z9sl","doc:\/\/SwiftUsd\/documentation\/OpenUSD\/Swift\/Bool\/init(_:)-83d6l","doc:\/\/SwiftUsd\/documentation\/OpenUSD\/Swift\/Bool\/init(_:)-84449","doc:\/\/SwiftUsd\/documentation\/OpenUSD\/Swift\/Bool\/init(_:)-85yzd","doc:\/\/SwiftUsd\/documentation\/OpenUSD\/Swift\/Bool\/init(_:)-8booq","doc:\/\/SwiftUsd\/documentation\/OpenUSD\/Swift\/Bool\/init(_:)-8e1kv","doc:\/\/SwiftUsd\/documentation\/OpenUSD\/Swift\/Bool\/init(_:)-8fpc0","doc:\/\/SwiftUsd\/documentation\/OpenUSD\/Swift\/Bool\/init(_:)-8fpmu","doc:\/\/SwiftUsd\/documentation\/OpenUSD\/Swift\/Bool\/init(_:)-8fxv6","doc:\/\/SwiftUsd\/documentation\/OpenUSD\/Swift\/Bool\/init(_:)-8lpgx","doc:\/\/SwiftUsd\/documentation\/OpenUSD\/Swift\/Bool\/init(_:)-8ppxf","doc:\/\/SwiftUsd\/documentation\/OpenUSD\/Swift\/Bool\/init(_:)-8q0js","doc:\/\/SwiftUsd\/documentation\/OpenUSD\/Swift\/Bool\/init(_:)-8q9wj","doc:\/\/SwiftUsd\/documentation\/OpenUSD\/Swift\/Bool\/init(_:)-8qii8","doc:\/\/SwiftUsd\/documentation\/OpenUSD\/Swift\/Bool\/init(_:)-8vd8m","doc:\/\/SwiftUsd\/documentation\/OpenUSD\/Swift\/Bool\/init(_:)-8zcdx","doc:\/\/SwiftUsd\/documentation\/OpenUSD\/Swift\/Bool\/init(_:)-91yiw","doc:\/\/SwiftUsd\/documentation\/OpenUSD\/Swift\/Bool\/init(_:)-92jm","doc:\/\/SwiftUsd\/documentation\/OpenUSD\/Swift\/Bool\/init(_:)-97fah","doc:\/\/SwiftUsd\/documentation\/OpenUSD\/Swift\/Bool\/init(_:)-97yxc","doc:\/\/SwiftUsd\/documentation\/OpenUSD\/Swift\/Bool\/init(_:)-9845o","doc:\/\/SwiftUsd\/documentation\/OpenUSD\/Swift\/Bool\/init(_:)-99xbt","doc:\/\/SwiftUsd\/documentation\/OpenUSD\/Swift\/Bool\/init(_:)-9aizs","doc:\/\/SwiftUsd\/documentation\/OpenUSD\/Swift\/Bool\/init(_:)-9ekuz","doc:\/\/SwiftUsd\/documentation\/OpenUSD\/Swift\/Bool\/init(_:)-9h3j9","doc:\/\/SwiftUsd\/documentation\/OpenUSD\/Swift\/Bool\/init(_:)-9kqfu","doc:\/\/SwiftUsd\/documentation\/OpenUSD\/Swift\/Bool\/init(_:)-9s4hm","doc:\/\/SwiftUsd\/documentation\/OpenUSD\/Swift\/Bool\/init(_:)-9w25","doc:\/\/SwiftUsd\/documentation\/OpenUSD\/Swift\/Bool\/init(_:)-9z2c0","doc:\/\/SwiftUsd\/documentation\/OpenUSD\/Swift\/Bool\/init(_:)-eg4y","doc:\/\/SwiftUsd\/documentation\/OpenUSD\/Swift\/Bool\/init(_:)-jwh4","doc:\/\/SwiftUsd\/documentation\/OpenUSD\/Swift\/Bool\/init(_:)-lryg","doc:\/\/SwiftUsd\/documentation\/OpenUSD\/Swift\/Bool\/init(_:)-qbsh","doc:\/\/SwiftUsd\/documentation\/OpenUSD\/Swift\/Bool\/init(_:)-qehe"],"generated":true}],"hierarchy":{"paths":[["doc:\/\/SwiftUsd\/documentation\/OpenUSD","doc:\/\/SwiftUsd\/documentation\/OpenUSD\/Swift"]]},"variants":[{"traits":[{"interfaceLanguage":"swift"}],"paths":["\/documentation\/openusd\/swift\/bool"]}],"primaryContentSections":[{"declarations":[{"tokens":[{"kind":"keyword","text":"extension"},{"kind":"text","text":" "},{"preciseIdentifier":"s:Sb","kind":"typeIdentifier","text":"Bool"}],"platforms":["macOS"],"languages":["swift"]}],"kind":"declarations"}],"metadata":{"externalID":"s:e:s:Sb7OpenUSDEySbSo021pxrInternal_v0_25_8__C10Reserved__O0061SdfHandlepxrSdfSpec_GzCBuCtaueVcfc","extendedModule":"Swift","modules":[{"name":"OpenUSD","relatedModules":["Swift"]}],"symbolKind":"extension","title":"Bool","role":"symbol","navigatorTitle":[{"kind":"identifier","text":"Bool"}],"fragments":[{"kind":"keyword","text":"extension"},{"kind":"text","text":" "},{"kind":"identifier","preciseIdentifier":"s:Sb","text":"Bool"}],"roleHeading":"Extended Structure"},"kind":"symbol","references":{"doc://SwiftUsd/documentation/OpenUSD/Swift/Bool/init(_:)-9aizs":{"role":"symbol","url":"\/documentation\/openusd\/swift\/bool\/init(_:)-9aizs","fragments":[{"kind":"identifier","text":"init"},{"kind":"text","text":"("},{"kind":"typeIdentifier","preciseIdentifier":"s:7OpenUSD3pxra","text":"pxr"},{"kind":"text","text":"."},{"kind":"typeIdentifier","preciseIdentifier":"c:@N@pxr@S@UsdLuxListAPI","text":"UsdLuxListAPI"},{"kind":"text","text":")"}],"identifier":"doc:\/\/SwiftUsd\/documentation\/OpenUSD\/Swift\/Bool\/init(_:)-9aizs","type":"topic","title":"init(_:)","abstract":[],"kind":"symbol"},"doc://SwiftUsd/documentation/OpenUSD/Swift/Bool/init(_:)-2e9j2":{"url":"\/documentation\/openusd\/swift\/bool\/init(_:)-2e9j2","title":"init(_:)","fragments":[{"text":"init","kind":"identifier"},{"text":"(","kind":"text"},{"preciseIdentifier":"s:7OpenUSD3pxra","text":"pxr","kind":"typeIdentifier"},{"text":".","kind":"text"},{"preciseIdentifier":"c:@N@pxr@S@UsdMediaSpatialAudio","text":"UsdMediaSpatialAudio","kind":"typeIdentifier"},{"text":")","kind":"text"}],"identifier":"doc:\/\/SwiftUsd\/documentation\/OpenUSD\/Swift\/Bool\/init(_:)-2e9j2","abstract":[],"role":"symbol","kind":"symbol","type":"topic"},"doc://SwiftUsd/documentation/OpenUSD/Swift/Bool/init(_:)-6dl38":{"url":"\/documentation\/openusd\/swift\/bool\/init(_:)-6dl38","role":"symbol","abstract":[{"type":"text","text":"Returns "},{"code":"true","type":"codeVoice"},{"type":"text","text":" is the spec has not expired"}],"type":"topic","identifier":"doc:\/\/SwiftUsd\/documentation\/OpenUSD\/Swift\/Bool\/init(_:)-6dl38","title":"init(_:)","fragments":[{"text":"init","kind":"identifier"},{"text":"(","kind":"text"},{"preciseIdentifier":"s:7OpenUSD3pxra","text":"pxr","kind":"typeIdentifier"},{"text":".","kind":"text"},{"preciseIdentifier":"c:pseudoRootSpec.h@N@pxr@T@SdfPseudoRootSpecHandle","text":"SdfPseudoRootSpecHandle","kind":"typeIdentifier"},{"text":")","kind":"text"}],"kind":"symbol"},"doc://SwiftUsd/documentation/OpenUSD/Swift":{"identifier":"doc:\/\/SwiftUsd\/documentation\/OpenUSD\/Swift","abstract":[],"url":"\/documentation\/openusd\/swift","title":"Swift","kind":"symbol","type":"topic","role":"collection"},"doc://SwiftUsd/documentation/OpenUSD/Swift/Bool/init(_:)-33e65":{"abstract":[],"fragments":[{"text":"init","kind":"identifier"},{"text":"(","kind":"text"},{"preciseIdentifier":"s:7OpenUSD3pxra","text":"pxr","kind":"typeIdentifier"},{"text":".","kind":"text"},{"preciseIdentifier":"c:@N@pxr@S@UsdLuxPortalLight","text":"UsdLuxPortalLight","kind":"typeIdentifier"},{"text":")","kind":"text"}],"type":"topic","title":"init(_:)","identifier":"doc:\/\/SwiftUsd\/documentation\/OpenUSD\/Swift\/Bool\/init(_:)-33e65","kind":"symbol","role":"symbol","url":"\/documentation\/openusd\/swift\/bool\/init(_:)-33e65"},"doc://SwiftUsd/documentation/OpenUSD/Swift/Bool/init(_:)-8fxv6":{"url":"\/documentation\/openusd\/swift\/bool\/init(_:)-8fxv6","type":"topic","fragments":[{"text":"init","kind":"identifier"},{"text":"(","kind":"text"},{"preciseIdentifier":"s:7OpenUSD3pxra","text":"pxr","kind":"typeIdentifier"},{"text":".","kind":"text"},{"preciseIdentifier":"c:@N@pxr@S@UsdMtlxMaterialXConfigAPI","text":"UsdMtlxMaterialXConfigAPI","kind":"typeIdentifier"},{"text":")","kind":"text"}],"identifier":"doc:\/\/SwiftUsd\/documentation\/OpenUSD\/Swift\/Bool\/init(_:)-8fxv6","role":"symbol","abstract":[],"kind":"symbol","title":"init(_:)"},"doc://SwiftUsd/documentation/OpenUSD/Swift/Bool/init(_:)-68s5g":{"identifier":"doc:\/\/SwiftUsd\/documentation\/OpenUSD\/Swift\/Bool\/init(_:)-68s5g","abstract":[{"type":"text","text":"Returns "},{"type":"codeVoice","code":"true"},{"type":"text","text":" is the spec has not expired"}],"title":"init(_:)","type":"topic","url":"\/documentation\/openusd\/swift\/bool\/init(_:)-68s5g","role":"symbol","fragments":[{"text":"init","kind":"identifier"},{"text":"(","kind":"text"},{"preciseIdentifier":"s:7OpenUSD3pxra","text":"pxr","kind":"typeIdentifier"},{"text":".","kind":"text"},{"preciseIdentifier":"c:types.h@N@pxr@T@SdfVariantSetSpecHandle","text":"SdfVariantSetSpecHandle","kind":"typeIdentifier"},{"text":")","kind":"text"}],"kind":"symbol"},"doc://SwiftUsd/documentation/OpenUSD/Swift/Bool/init(_:)-6xnyv":{"fragments":[{"text":"init","kind":"identifier"},{"text":"(","kind":"text"},{"text":"pxr","kind":"typeIdentifier","preciseIdentifier":"s:7OpenUSD3pxra"},{"text":".","kind":"text"},{"text":"UsdHydraGenerativeProceduralAPI","kind":"typeIdentifier","preciseIdentifier":"c:@N@pxr@S@UsdHydraGenerativeProceduralAPI"},{"text":")","kind":"text"}],"role":"symbol","abstract":[],"identifier":"doc:\/\/SwiftUsd\/documentation\/OpenUSD\/Swift\/Bool\/init(_:)-6xnyv","kind":"symbol","title":"init(_:)","url":"\/documentation\/openusd\/swift\/bool\/init(_:)-6xnyv","type":"topic"},"doc://SwiftUsd/documentation/OpenUSD/Swift/Bool/init(_:)-7u766":{"fragments":[{"text":"init","kind":"identifier"},{"text":"(","kind":"text"},{"preciseIdentifier":"s:7OpenUSD3pxra","text":"pxr","kind":"typeIdentifier"},{"text":".","kind":"text"},{"preciseIdentifier":"c:@N@pxr@S@ArResolvedPath","text":"ArResolvedPath","kind":"typeIdentifier"},{"text":")","kind":"text"}],"role":"symbol","type":"topic","abstract":[{"type":"text","text":"Returns "},{"code":"true","type":"codeVoice"},{"type":"text","text":" if the resolved path is non-empty"}],"kind":"symbol","identifier":"doc:\/\/SwiftUsd\/documentation\/OpenUSD\/Swift\/Bool\/init(_:)-7u766","title":"init(_:)","url":"\/documentation\/openusd\/swift\/bool\/init(_:)-7u766"},"doc://SwiftUsd/documentation/OpenUSD/Swift/Bool/init(_:)-63kny":{"fragments":[{"text":"init","kind":"identifier"},{"text":"(","kind":"text"},{"text":"some","kind":"keyword"},{"text":" ","kind":"text"},{"preciseIdentifier":"c:@N@Overlay","text":"Overlay","kind":"typeIdentifier"},{"text":".","kind":"text"},{"preciseIdentifier":"s:So7OverlayO7OpenUSDE17_TfRefPtrProtocolP","text":"_TfRefPtrProtocol","kind":"typeIdentifier"},{"text":")","kind":"text"}],"role":"symbol","title":"init(_:)","url":"\/documentation\/openusd\/swift\/bool\/init(_:)-63kny","identifier":"doc:\/\/SwiftUsd\/documentation\/OpenUSD\/Swift\/Bool\/init(_:)-63kny","kind":"symbol","abstract":[{"type":"text","text":"Returns "},{"type":"codeVoice","code":"true"},{"type":"text","text":" if the pointer is not null"}],"type":"topic"},"doc://SwiftUsd/documentation/OpenUSD/Swift/Bool/init(_:)-8e1kv":{"abstract":[],"fragments":[{"text":"init","kind":"identifier"},{"text":"(","kind":"text"},{"preciseIdentifier":"s:7OpenUSD3pxra","text":"pxr","kind":"typeIdentifier"},{"text":".","kind":"text"},{"preciseIdentifier":"c:@N@pxr@S@UsdLuxShadowAPI","text":"UsdLuxShadowAPI","kind":"typeIdentifier"},{"text":")","kind":"text"}],"title":"init(_:)","type":"topic","identifier":"doc:\/\/SwiftUsd\/documentation\/OpenUSD\/Swift\/Bool\/init(_:)-8e1kv","kind":"symbol","role":"symbol","url":"\/documentation\/openusd\/swift\/bool\/init(_:)-8e1kv"},"doc://SwiftUsd/documentation/OpenUSD/Swift/Bool/init(_:)-lryg":{"kind":"symbol","url":"\/documentation\/openusd\/swift\/bool\/init(_:)-lryg","abstract":[],"title":"init(_:)","type":"topic","identifier":"doc:\/\/SwiftUsd\/documentation\/OpenUSD\/Swift\/Bool\/init(_:)-lryg","role":"symbol","fragments":[{"kind":"identifier","text":"init"},{"kind":"text","text":"("},{"kind":"typeIdentifier","preciseIdentifier":"s:7OpenUSD3pxra","text":"pxr"},{"kind":"text","text":"."},{"kind":"typeIdentifier","preciseIdentifier":"c:@N@pxr@S@UsdPhysicsMeshCollisionAPI","text":"UsdPhysicsMeshCollisionAPI"},{"kind":"text","text":")"}]},"doc://SwiftUsd/documentation/OpenUSD/Swift/Bool/init(_:)-3t28w":{"kind":"symbol","title":"init(_:)","url":"\/documentation\/openusd\/swift\/bool\/init(_:)-3t28w","abstract":[],"type":"topic","role":"symbol","identifier":"doc:\/\/SwiftUsd\/documentation\/OpenUSD\/Swift\/Bool\/init(_:)-3t28w","fragments":[{"text":"init","kind":"identifier"},{"text":"(","kind":"text"},{"preciseIdentifier":"s:7OpenUSD3pxra","text":"pxr","kind":"typeIdentifier"},{"text":".","kind":"text"},{"preciseIdentifier":"c:@N@pxr@S@UsdClipsAPI","text":"UsdClipsAPI","kind":"typeIdentifier"},{"text":")","kind":"text"}]},"doc://SwiftUsd/documentation/OpenUSD/Swift/Bool/init(_:)-4hsn3":{"kind":"symbol","title":"init(_:)","url":"\/documentation\/openusd\/swift\/bool\/init(_:)-4hsn3","abstract":[],"type":"topic","role":"symbol","identifier":"doc:\/\/SwiftUsd\/documentation\/OpenUSD\/Swift\/Bool\/init(_:)-4hsn3","fragments":[{"text":"init","kind":"identifier"},{"text":"(","kind":"text"},{"preciseIdentifier":"s:7OpenUSD3pxra","text":"pxr","kind":"typeIdentifier"},{"text":".","kind":"text"},{"preciseIdentifier":"c:@N@pxr@S@UsdGeomPointInstancer","text":"UsdGeomPointInstancer","kind":"typeIdentifier"},{"text":")","kind":"text"}]},"doc://SwiftUsd/documentation/OpenUSD/Swift/Bool/init(_:)-eg4y":{"identifier":"doc:\/\/SwiftUsd\/documentation\/OpenUSD\/Swift\/Bool\/init(_:)-eg4y","abstract":[],"role":"symbol","fragments":[{"text":"init","kind":"identifier"},{"text":"(","kind":"text"},{"preciseIdentifier":"s:7OpenUSD3pxra","text":"pxr","kind":"typeIdentifier"},{"text":".","kind":"text"},{"preciseIdentifier":"c:@N@pxr@S@UsdRenderProduct","text":"UsdRenderProduct","kind":"typeIdentifier"},{"text":")","kind":"text"}],"type":"topic","kind":"symbol","title":"init(_:)","url":"\/documentation\/openusd\/swift\/bool\/init(_:)-eg4y"},"doc://SwiftUsd/documentation/OpenUSD/Swift/Bool/init(_:)-3kyk2":{"identifier":"doc:\/\/SwiftUsd\/documentation\/OpenUSD\/Swift\/Bool\/init(_:)-3kyk2","kind":"symbol","abstract":[],"fragments":[{"text":"init","kind":"identifier"},{"text":"(","kind":"text"},{"preciseIdentifier":"s:7OpenUSD3pxra","text":"pxr","kind":"typeIdentifier"},{"text":".","kind":"text"},{"preciseIdentifier":"c:@N@pxr@S@UsdLuxCylinderLight","text":"UsdLuxCylinderLight","kind":"typeIdentifier"},{"text":")","kind":"text"}],"title":"init(_:)","url":"\/documentation\/openusd\/swift\/bool\/init(_:)-3kyk2","type":"topic","role":"symbol"},"doc://SwiftUsd/documentation/OpenUSD/Swift/Bool/init(_:)-18la":{"url":"\/documentation\/openusd\/swift\/bool\/init(_:)-18la","identifier":"doc:\/\/SwiftUsd\/documentation\/OpenUSD\/Swift\/Bool\/init(_:)-18la","kind":"symbol","type":"topic","title":"init(_:)","role":"symbol","fragments":[{"text":"init","kind":"identifier"},{"text":"(","kind":"text"},{"preciseIdentifier":"s:7OpenUSD3pxra","text":"pxr","kind":"typeIdentifier"},{"text":".","kind":"text"},{"preciseIdentifier":"c:@N@pxr@S@UsdGeomPrimvarsAPI","text":"UsdGeomPrimvarsAPI","kind":"typeIdentifier"},{"text":")","kind":"text"}],"abstract":[]},"doc://SwiftUsd/documentation/OpenUSD/Swift/Bool/init(_:)-1vx95":{"kind":"symbol","role":"symbol","fragments":[{"text":"init","kind":"identifier"},{"text":"(","kind":"text"},{"text":"pxr","kind":"typeIdentifier","preciseIdentifier":"s:7OpenUSD3pxra"},{"text":".","kind":"text"},{"text":"UsdLuxNonboundableLightBase","kind":"typeIdentifier","preciseIdentifier":"c:@N@pxr@S@UsdLuxNonboundableLightBase"},{"text":")","kind":"text"}],"abstract":[],"title":"init(_:)","type":"topic","url":"\/documentation\/openusd\/swift\/bool\/init(_:)-1vx95","identifier":"doc:\/\/SwiftUsd\/documentation\/OpenUSD\/Swift\/Bool\/init(_:)-1vx95"},"doc://SwiftUsd/documentation/OpenUSD/Swift/Bool/init(_:)-97yxc":{"url":"\/documentation\/openusd\/swift\/bool\/init(_:)-97yxc","type":"topic","kind":"symbol","identifier":"doc:\/\/SwiftUsd\/documentation\/OpenUSD\/Swift\/Bool\/init(_:)-97yxc","role":"symbol","title":"init(_:)","abstract":[],"fragments":[{"text":"init","kind":"identifier"},{"text":"(","kind":"text"},{"preciseIdentifier":"s:7OpenUSD3pxra","text":"pxr","kind":"typeIdentifier"},{"text":".","kind":"text"},{"preciseIdentifier":"c:@N@pxr@S@UsdShadeCoordSysAPI","text":"UsdShadeCoordSysAPI","kind":"typeIdentifier"},{"text":")","kind":"text"}]},"doc://SwiftUsd/documentation/OpenUSD/Swift/Bool/init(_:)-6m3s1":{"type":"topic","fragments":[{"text":"init","kind":"identifier"},{"text":"(","kind":"text"},{"preciseIdentifier":"s:7OpenUSD3pxra","text":"pxr","kind":"typeIdentifier"},{"text":".","kind":"text"},{"preciseIdentifier":"c:@N@pxr@S@UsdRelationship","text":"UsdRelationship","kind":"typeIdentifier"},{"text":")","kind":"text"}],"url":"\/documentation\/openusd\/swift\/bool\/init(_:)-6m3s1","kind":"symbol","identifier":"doc:\/\/SwiftUsd\/documentation\/OpenUSD\/Swift\/Bool\/init(_:)-6m3s1","abstract":[{"type":"text","text":"Returns "},{"code":"true","type":"codeVoice"},{"type":"text","text":" if the "},{"code":"UsdRelationship","type":"codeVoice"},{"type":"text","text":" is valid"}],"title":"init(_:)","role":"symbol"},"doc://SwiftUsd/documentation/OpenUSD/Swift/Bool/init(_:)-447kh":{"kind":"symbol","abstract":[],"role":"symbol","identifier":"doc:\/\/SwiftUsd\/documentation\/OpenUSD\/Swift\/Bool\/init(_:)-447kh","type":"topic","title":"init(_:)","url":"\/documentation\/openusd\/swift\/bool\/init(_:)-447kh","fragments":[{"text":"init","kind":"identifier"},{"text":"(","kind":"text"},{"preciseIdentifier":"s:7OpenUSD3pxra","text":"pxr","kind":"typeIdentifier"},{"text":".","kind":"text"},{"preciseIdentifier":"c:@N@pxr@S@UsdGeomCamera","text":"UsdGeomCamera","kind":"typeIdentifier"},{"text":")","kind":"text"}]},"doc://SwiftUsd/documentation/OpenUSD/Swift/Bool/init(_:)-6vhi3":{"role":"symbol","fragments":[{"text":"init","kind":"identifier"},{"text":"(","kind":"text"},{"preciseIdentifier":"s:7OpenUSD3pxra","text":"pxr","kind":"typeIdentifier"},{"text":".","kind":"text"},{"preciseIdentifier":"c:@N@pxr@S@UsdVolOpenVDBAsset","text":"UsdVolOpenVDBAsset","kind":"typeIdentifier"},{"text":")","kind":"text"}],"kind":"symbol","url":"\/documentation\/openusd\/swift\/bool\/init(_:)-6vhi3","type":"topic","abstract":[],"identifier":"doc:\/\/SwiftUsd\/documentation\/OpenUSD\/Swift\/Bool\/init(_:)-6vhi3","title":"init(_:)"},"doc://SwiftUsd/documentation/OpenUSD/Swift/Bool/init(_:)-5785k":{"kind":"symbol","role":"symbol","fragments":[{"text":"init","kind":"identifier"},{"text":"(","kind":"text"},{"preciseIdentifier":"s:7OpenUSD3pxra","text":"pxr","kind":"typeIdentifier"},{"text":".","kind":"text"},{"preciseIdentifier":"c:@N@pxr@S@UsdPhysicsScene","text":"UsdPhysicsScene","kind":"typeIdentifier"},{"text":")","kind":"text"}],"identifier":"doc:\/\/SwiftUsd\/documentation\/OpenUSD\/Swift\/Bool\/init(_:)-5785k","url":"\/documentation\/openusd\/swift\/bool\/init(_:)-5785k","type":"topic","abstract":[],"title":"init(_:)"},"doc://SwiftUsd/documentation/OpenUSD/Swift/Bool/init(_:)-3gvxw":{"role":"symbol","url":"\/documentation\/openusd\/swift\/bool\/init(_:)-3gvxw","identifier":"doc:\/\/SwiftUsd\/documentation\/OpenUSD\/Swift\/Bool\/init(_:)-3gvxw","kind":"symbol","fragments":[{"text":"init","kind":"identifier"},{"text":"(","kind":"text"},{"preciseIdentifier":"s:7OpenUSD3pxra","text":"pxr","kind":"typeIdentifier"},{"text":".","kind":"text"},{"preciseIdentifier":"c:@N@pxr@S@UsdPhysicsDistanceJoint","text":"UsdPhysicsDistanceJoint","kind":"typeIdentifier"},{"text":")","kind":"text"}],"title":"init(_:)","abstract":[],"type":"topic"},"doc://SwiftUsd/documentation/OpenUSD/Swift/Bool/init(_:)-77uad":{"fragments":[{"text":"init","kind":"identifier"},{"text":"(","kind":"text"},{"preciseIdentifier":"s:7OpenUSD3pxra","text":"pxr","kind":"typeIdentifier"},{"text":".","kind":"text"},{"preciseIdentifier":"c:@N@pxr@S@UsdSemanticsLabelsAPI","text":"UsdSemanticsLabelsAPI","kind":"typeIdentifier"},{"text":")","kind":"text"}],"kind":"symbol","title":"init(_:)","type":"topic","url":"\/documentation\/openusd\/swift\/bool\/init(_:)-77uad","role":"symbol","identifier":"doc:\/\/SwiftUsd\/documentation\/OpenUSD\/Swift\/Bool\/init(_:)-77uad","abstract":[]},"doc://SwiftUsd/documentation/OpenUSD/Swift/Bool/init(_:)-9z2c0":{"role":"symbol","kind":"symbol","title":"init(_:)","type":"topic","url":"\/documentation\/openusd\/swift\/bool\/init(_:)-9z2c0","abstract":[{"type":"text","text":"Returns "},{"code":"true","type":"codeVoice"},{"type":"text","text":" is the spec has not expired"}],"identifier":"doc:\/\/SwiftUsd\/documentation\/OpenUSD\/Swift\/Bool\/init(_:)-9z2c0","fragments":[{"text":"init","kind":"identifier"},{"text":"(","kind":"text"},{"preciseIdentifier":"s:7OpenUSD3pxra","text":"pxr","kind":"typeIdentifier"},{"text":".","kind":"text"},{"preciseIdentifier":"c:types.h@N@pxr@T@SdfRelationshipSpecHandle","text":"SdfRelationshipSpecHandle","kind":"typeIdentifier"},{"text":")","kind":"text"}]},"doc://SwiftUsd/documentation/OpenUSD/Swift/Bool/init(_:)-19r9m":{"url":"\/documentation\/openusd\/swift\/bool\/init(_:)-19r9m","role":"symbol","identifier":"doc:\/\/SwiftUsd\/documentation\/OpenUSD\/Swift\/Bool\/init(_:)-19r9m","kind":"symbol","type":"topic","fragments":[{"text":"init","kind":"identifier"},{"text":"(","kind":"text"},{"preciseIdentifier":"s:7OpenUSD3pxra","text":"pxr","kind":"typeIdentifier"},{"text":".","kind":"text"},{"preciseIdentifier":"c:@N@pxr@S@UsdPhysicsArticulationRootAPI","text":"UsdPhysicsArticulationRootAPI","kind":"typeIdentifier"},{"text":")","kind":"text"}],"title":"init(_:)","abstract":[]},"doc://SwiftUsd/documentation/OpenUSD/Swift/Bool/init(_:)-84449":{"type":"topic","title":"init(_:)","fragments":[{"text":"init","kind":"identifier"},{"text":"(","kind":"text"},{"preciseIdentifier":"s:7OpenUSD3pxra","text":"pxr","kind":"typeIdentifier"},{"text":".","kind":"text"},{"preciseIdentifier":"c:@N@pxr@S@UsdAPISchemaBase","text":"UsdAPISchemaBase","kind":"typeIdentifier"},{"text":")","kind":"text"}],"url":"\/documentation\/openusd\/swift\/bool\/init(_:)-84449","abstract":[],"role":"symbol","kind":"symbol","identifier":"doc:\/\/SwiftUsd\/documentation\/OpenUSD\/Swift\/Bool\/init(_:)-84449"},"doc://SwiftUsd/documentation/OpenUSD/Swift/Bool/init(_:)-12f6s":{"title":"init(_:)","role":"symbol","kind":"symbol","fragments":[{"text":"init","kind":"identifier"},{"text":"(","kind":"text"},{"preciseIdentifier":"s:7OpenUSD3pxra","text":"pxr","kind":"typeIdentifier"},{"text":".","kind":"text"},{"preciseIdentifier":"c:@N@pxr@S@UsdGeomPointBased","text":"UsdGeomPointBased","kind":"typeIdentifier"},{"text":")","kind":"text"}],"type":"topic","identifier":"doc:\/\/SwiftUsd\/documentation\/OpenUSD\/Swift\/Bool\/init(_:)-12f6s","abstract":[],"url":"\/documentation\/openusd\/swift\/bool\/init(_:)-12f6s"},"doc://SwiftUsd/documentation/OpenUSD/Swift/Bool/init(_:)-8qii8":{"type":"topic","identifier":"doc:\/\/SwiftUsd\/documentation\/OpenUSD\/Swift\/Bool\/init(_:)-8qii8","url":"\/documentation\/openusd\/swift\/bool\/init(_:)-8qii8","kind":"symbol","abstract":[],"fragments":[{"text":"init","kind":"identifier"},{"text":"(","kind":"text"},{"preciseIdentifier":"s:7OpenUSD3pxra","text":"pxr","kind":"typeIdentifier"},{"text":".","kind":"text"},{"preciseIdentifier":"c:@N@pxr@S@UsdUIAccessibilityAPI","text":"UsdUIAccessibilityAPI","kind":"typeIdentifier"},{"text":")","kind":"text"}],"role":"symbol","title":"init(_:)"},"doc://SwiftUsd/documentation/OpenUSD/Swift/Bool/init(_:)-85yzd":{"abstract":[],"role":"symbol","kind":"symbol","identifier":"doc:\/\/SwiftUsd\/documentation\/OpenUSD\/Swift\/Bool\/init(_:)-85yzd","fragments":[{"text":"init","kind":"identifier"},{"text":"(","kind":"text"},{"preciseIdentifier":"s:7OpenUSD3pxra","text":"pxr","kind":"typeIdentifier"},{"text":".","kind":"text"},{"preciseIdentifier":"c:@N@pxr@S@UsdShadeNodeDefAPI","text":"UsdShadeNodeDefAPI","kind":"typeIdentifier"},{"text":")","kind":"text"}],"title":"init(_:)","url":"\/documentation\/openusd\/swift\/bool\/init(_:)-85yzd","type":"topic"},"doc://SwiftUsd/documentation/OpenUSD/Swift/Bool/init(_:)-9kqfu":{"fragments":[{"text":"init","kind":"identifier"},{"text":"(","kind":"text"},{"preciseIdentifier":"s:7OpenUSD3pxra","text":"pxr","kind":"typeIdentifier"},{"text":".","kind":"text"},{"preciseIdentifier":"c:types.h@N@pxr@T@SdfPrimSpecHandle","text":"SdfPrimSpecHandle","kind":"typeIdentifier"},{"text":")","kind":"text"}],"abstract":[{"type":"text","text":"Returns "},{"code":"true","type":"codeVoice"},{"type":"text","text":" is the spec has not expired"}],"title":"init(_:)","kind":"symbol","url":"\/documentation\/openusd\/swift\/bool\/init(_:)-9kqfu","identifier":"doc:\/\/SwiftUsd\/documentation\/OpenUSD\/Swift\/Bool\/init(_:)-9kqfu","type":"topic","role":"symbol"},"doc://SwiftUsd/documentation/OpenUSD/Swift/Bool/init(_:)-5h9cb":{"type":"topic","abstract":[],"identifier":"doc:\/\/SwiftUsd\/documentation\/OpenUSD\/Swift\/Bool\/init(_:)-5h9cb","role":"symbol","url":"\/documentation\/openusd\/swift\/bool\/init(_:)-5h9cb","title":"init(_:)","fragments":[{"text":"init","kind":"identifier"},{"text":"(","kind":"text"},{"preciseIdentifier":"s:7OpenUSD3pxra","text":"pxr","kind":"typeIdentifier"},{"text":".","kind":"text"},{"preciseIdentifier":"c:@N@pxr@S@UsdSkelBindingAPI","text":"UsdSkelBindingAPI","kind":"typeIdentifier"},{"text":")","kind":"text"}],"kind":"symbol"},"doc://SwiftUsd/documentation/OpenUSD/Swift/Bool/init(_:)-22foc":{"kind":"symbol","url":"\/documentation\/openusd\/swift\/bool\/init(_:)-22foc","identifier":"doc:\/\/SwiftUsd\/documentation\/OpenUSD\/Swift\/Bool\/init(_:)-22foc","type":"topic","fragments":[{"text":"init","kind":"identifier"},{"text":"(","kind":"text"},{"preciseIdentifier":"s:7OpenUSD3pxra","text":"pxr","kind":"typeIdentifier"},{"text":".","kind":"text"},{"preciseIdentifier":"c:@N@pxr@S@UsdRiStatementsAPI","text":"UsdRiStatementsAPI","kind":"typeIdentifier"},{"text":")","kind":"text"}],"abstract":[],"title":"init(_:)","role":"symbol"},"doc://SwiftUsd/documentation/OpenUSD/Swift/Bool/init(_:)-64tmj":{"title":"init(_:)","identifier":"doc:\/\/SwiftUsd\/documentation\/OpenUSD\/Swift\/Bool\/init(_:)-64tmj","role":"symbol","kind":"symbol","url":"\/documentation\/openusd\/swift\/bool\/init(_:)-64tmj","fragments":[{"text":"init","kind":"identifier"},{"text":"(","kind":"text"},{"preciseIdentifier":"s:7OpenUSD3pxra","text":"pxr","kind":"typeIdentifier"},{"text":".","kind":"text"},{"preciseIdentifier":"c:types.h@N@pxr@T@SdfPropertySpecHandle","text":"SdfPropertySpecHandle","kind":"typeIdentifier"},{"text":")","kind":"text"}],"abstract":[{"type":"text","text":"Returns "},{"type":"codeVoice","code":"true"},{"type":"text","text":" is the spec has not expired"}],"type":"topic"},"doc://SwiftUsd/documentation/OpenUSD/Swift/Bool/init(_:)-5pgft":{"fragments":[{"text":"init","kind":"identifier"},{"text":"(","kind":"text"},{"preciseIdentifier":"s:7OpenUSD3pxra","text":"pxr","kind":"typeIdentifier"},{"text":".","kind":"text"},{"preciseIdentifier":"c:@N@pxr@S@UsdLuxRectLight","text":"UsdLuxRectLight","kind":"typeIdentifier"},{"text":")","kind":"text"}],"abstract":[],"type":"topic","kind":"symbol","url":"\/documentation\/openusd\/swift\/bool\/init(_:)-5pgft","role":"symbol","title":"init(_:)","identifier":"doc:\/\/SwiftUsd\/documentation\/OpenUSD\/Swift\/Bool\/init(_:)-5pgft"},"doc://SwiftUsd/documentation/OpenUSD/Swift/Bool/init(_:)-4u74q":{"kind":"symbol","type":"topic","role":"symbol","title":"init(_:)","abstract":[{"type":"text","text":"Returns "},{"type":"codeVoice","code":"true"},{"type":"text","text":" is the spec has not expired"}],"identifier":"doc:\/\/SwiftUsd\/documentation\/OpenUSD\/Swift\/Bool\/init(_:)-4u74q","url":"\/documentation\/openusd\/swift\/bool\/init(_:)-4u74q","fragments":[{"text":"init","kind":"identifier"},{"text":"(","kind":"text"},{"preciseIdentifier":"s:7OpenUSD3pxra","text":"pxr","kind":"typeIdentifier"},{"text":".","kind":"text"},{"preciseIdentifier":"c:types.h@N@pxr@T@SdfVariantSpecHandle","text":"SdfVariantSpecHandle","kind":"typeIdentifier"},{"text":")","kind":"text"}]},"doc://SwiftUsd/documentation/OpenUSD/Swift/Bool/init(_:)-32k7q":{"kind":"symbol","type":"topic","role":"symbol","title":"init(_:)","abstract":[],"identifier":"doc:\/\/SwiftUsd\/documentation\/OpenUSD\/Swift\/Bool\/init(_:)-32k7q","url":"\/documentation\/openusd\/swift\/bool\/init(_:)-32k7q","fragments":[{"text":"init","kind":"identifier"},{"text":"(","kind":"text"},{"preciseIdentifier":"s:7OpenUSD3pxra","text":"pxr","kind":"typeIdentifier"},{"text":".","kind":"text"},{"preciseIdentifier":"c:@N@pxr@S@UsdLuxDiskLight","text":"UsdLuxDiskLight","kind":"typeIdentifier"},{"text":")","kind":"text"}]},"doc://SwiftUsd/documentation/OpenUSD/Swift/Bool/init(_:)-2go3b":{"title":"init(_:)","identifier":"doc:\/\/SwiftUsd\/documentation\/OpenUSD\/Swift\/Bool\/init(_:)-2go3b","role":"symbol","kind":"symbol","url":"\/documentation\/openusd\/swift\/bool\/init(_:)-2go3b","fragments":[{"text":"init","kind":"identifier"},{"text":"(","kind":"text"},{"preciseIdentifier":"s:7OpenUSD3pxra","text":"pxr","kind":"typeIdentifier"},{"text":".","kind":"text"},{"preciseIdentifier":"c:@N@pxr@S@UsdPrim","text":"UsdPrim","kind":"typeIdentifier"},{"text":")","kind":"text"}],"abstract":[{"type":"text","text":"Returns "},{"type":"codeVoice","code":"true"},{"type":"text","text":" if the "},{"type":"codeVoice","code":"UsdPrim"},{"type":"text","text":" is valid"}],"type":"topic"},"doc://SwiftUsd/documentation/OpenUSD/Swift/Bool/init(_:)-16jvq":{"identifier":"doc:\/\/SwiftUsd\/documentation\/OpenUSD\/Swift\/Bool\/init(_:)-16jvq","abstract":[],"role":"symbol","url":"\/documentation\/openusd\/swift\/bool\/init(_:)-16jvq","type":"topic","fragments":[{"text":"init","kind":"identifier"},{"text":"(","kind":"text"},{"preciseIdentifier":"s:7OpenUSD3pxra","text":"pxr","kind":"typeIdentifier"},{"text":".","kind":"text"},{"preciseIdentifier":"c:@N@pxr@S@UsdUIBackdrop","text":"UsdUIBackdrop","kind":"typeIdentifier"},{"text":")","kind":"text"}],"title":"init(_:)","kind":"symbol"},"doc://SwiftUsd/documentation/OpenUSD/Swift/Bool/init(_:)-1thf8":{"identifier":"doc:\/\/SwiftUsd\/documentation\/OpenUSD\/Swift\/Bool\/init(_:)-1thf8","abstract":[],"role":"symbol","url":"\/documentation\/openusd\/swift\/bool\/init(_:)-1thf8","type":"topic","fragments":[{"text":"init","kind":"identifier"},{"text":"(","kind":"text"},{"preciseIdentifier":"s:7OpenUSD3pxra","text":"pxr","kind":"typeIdentifier"},{"text":".","kind":"text"},{"preciseIdentifier":"c:@N@pxr@S@UsdShadeMaterial","text":"UsdShadeMaterial","kind":"typeIdentifier"},{"text":")","kind":"text"}],"title":"init(_:)","kind":"symbol"},"doc://SwiftUsd/documentation/OpenUSD/Swift/Bool/init(_:)-9845o":{"fragments":[{"text":"init","kind":"identifier"},{"text":"(","kind":"text"},{"preciseIdentifier":"s:7OpenUSD3pxra","text":"pxr","kind":"typeIdentifier"},{"text":".","kind":"text"},{"preciseIdentifier":"c:@N@pxr@S@UsdGeomSphere","text":"UsdGeomSphere","kind":"typeIdentifier"},{"text":")","kind":"text"}],"abstract":[],"kind":"symbol","title":"init(_:)","identifier":"doc:\/\/SwiftUsd\/documentation\/OpenUSD\/Swift\/Bool\/init(_:)-9845o","type":"topic","url":"\/documentation\/openusd\/swift\/bool\/init(_:)-9845o","role":"symbol"},"doc://SwiftUsd/documentation/OpenUSD/Swift/Bool/init(_:)-1owj5":{"title":"init(_:)","identifier":"doc:\/\/SwiftUsd\/documentation\/OpenUSD\/Swift\/Bool\/init(_:)-1owj5","role":"symbol","kind":"symbol","url":"\/documentation\/openusd\/swift\/bool\/init(_:)-1owj5","fragments":[{"text":"init","kind":"identifier"},{"text":"(","kind":"text"},{"preciseIdentifier":"s:7OpenUSD3pxra","text":"pxr","kind":"typeIdentifier"},{"text":".","kind":"text"},{"preciseIdentifier":"c:@N@pxr@S@UsdAttribute","text":"UsdAttribute","kind":"typeIdentifier"},{"text":")","kind":"text"}],"abstract":[{"type":"text","text":"Returns "},{"type":"codeVoice","code":"true"},{"type":"text","text":" if the "},{"type":"codeVoice","code":"UsdAttribute"},{"type":"text","text":" is valid"}],"type":"topic"},"doc://SwiftUsd/documentation/OpenUSD/Swift/Bool/init(_:)-6t6an":{"title":"init(_:)","role":"symbol","url":"\/documentation\/openusd\/swift\/bool\/init(_:)-6t6an","fragments":[{"text":"init","kind":"identifier"},{"text":"(","kind":"text"},{"preciseIdentifier":"s:7OpenUSD3pxra","text":"pxr","kind":"typeIdentifier"},{"text":".","kind":"text"},{"preciseIdentifier":"c:@N@pxr@S@UsdGeomCapsule","text":"UsdGeomCapsule","kind":"typeIdentifier"},{"text":")","kind":"text"}],"identifier":"doc:\/\/SwiftUsd\/documentation\/OpenUSD\/Swift\/Bool\/init(_:)-6t6an","type":"topic","kind":"symbol","abstract":[]},"doc://SwiftUsd/documentation/OpenUSD/Swift/Bool/init(_:)-7ohk3":{"title":"init(_:)","type":"topic","identifier":"doc:\/\/SwiftUsd\/documentation\/OpenUSD\/Swift\/Bool\/init(_:)-7ohk3","role":"symbol","fragments":[{"text":"init","kind":"identifier"},{"text":"(","kind":"text"},{"preciseIdentifier":"s:7OpenUSD3pxra","text":"pxr","kind":"typeIdentifier"},{"text":".","kind":"text"},{"preciseIdentifier":"c:@N@pxr@S@UsdGeomCapsule_1","text":"UsdGeomCapsule_1","kind":"typeIdentifier"},{"text":")","kind":"text"}],"abstract":[],"kind":"symbol","url":"\/documentation\/openusd\/swift\/bool\/init(_:)-7ohk3"},"doc://SwiftUsd/documentation/OpenUSD/Swift/Bool/init(_:)-27z53":{"role":"symbol","title":"init(_:)","fragments":[{"text":"init","kind":"identifier"},{"text":"(","kind":"text"},{"preciseIdentifier":"s:7OpenUSD3pxra","text":"pxr","kind":"typeIdentifier"},{"text":".","kind":"text"},{"preciseIdentifier":"c:@N@pxr@S@UsdGeomXform","text":"UsdGeomXform","kind":"typeIdentifier"},{"text":")","kind":"text"}],"abstract":[],"type":"topic","url":"\/documentation\/openusd\/swift\/bool\/init(_:)-27z53","identifier":"doc:\/\/SwiftUsd\/documentation\/OpenUSD\/Swift\/Bool\/init(_:)-27z53","kind":"symbol"},"doc://SwiftUsd/documentation/OpenUSD/Swift/Bool/init(_:)-3igwk":{"fragments":[{"text":"init","kind":"identifier"},{"text":"(","kind":"text"},{"preciseIdentifier":"s:7OpenUSD3pxra","text":"pxr","kind":"typeIdentifier"},{"text":".","kind":"text"},{"preciseIdentifier":"c:@N@pxr@S@UsdRenderSettings","text":"UsdRenderSettings","kind":"typeIdentifier"},{"text":")","kind":"text"}],"kind":"symbol","type":"topic","title":"init(_:)","url":"\/documentation\/openusd\/swift\/bool\/init(_:)-3igwk","role":"symbol","abstract":[],"identifier":"doc:\/\/SwiftUsd\/documentation\/OpenUSD\/Swift\/Bool\/init(_:)-3igwk"},"doc://SwiftUsd/documentation/OpenUSD/Swift/Bool/init(_:)-4kn15":{"title":"init(_:)","url":"\/documentation\/openusd\/swift\/bool\/init(_:)-4kn15","fragments":[{"text":"init","kind":"identifier"},{"text":"(","kind":"text"},{"text":"pxr","preciseIdentifier":"s:7OpenUSD3pxra","kind":"typeIdentifier"},{"text":".","kind":"text"},{"text":"UsdCollectionAPI","preciseIdentifier":"c:@N@pxr@S@UsdCollectionAPI","kind":"typeIdentifier"},{"text":")","kind":"text"}],"identifier":"doc:\/\/SwiftUsd\/documentation\/OpenUSD\/Swift\/Bool\/init(_:)-4kn15","abstract":[],"role":"symbol","kind":"symbol","type":"topic"},"doc://SwiftUsd/documentation/OpenUSD/Swift/Bool/init(_:)-6azcc":{"type":"topic","title":"init(_:)","abstract":[{"type":"text","text":"Returns "},{"code":"true","type":"codeVoice"},{"type":"text","text":" if the pointer is not null."}],"role":"symbol","identifier":"doc:\/\/SwiftUsd\/documentation\/OpenUSD\/Swift\/Bool\/init(_:)-6azcc","url":"\/documentation\/openusd\/swift\/bool\/init(_:)-6azcc","fragments":[{"text":"init","kind":"identifier"},{"text":"(","kind":"text"},{"text":"some","kind":"keyword"},{"text":" ","kind":"text"},{"preciseIdentifier":"c:@N@Overlay","text":"Overlay","kind":"typeIdentifier"},{"text":".","kind":"text"},{"preciseIdentifier":"s:So7OverlayO7OpenUSDE18_TfWeakPtrProtocolP","text":"_TfWeakPtrProtocol","kind":"typeIdentifier"},{"text":")","kind":"text"}],"kind":"symbol"},"doc://SwiftUsd/documentation/OpenUSD/Swift/Bool/init(_:)-5q3cx":{"abstract":[{"type":"text","text":"Returns "},{"type":"codeVoice","code":"true"},{"type":"text","text":" if the pointer is not null."}],"kind":"symbol","title":"init(_:)","url":"\/documentation\/openusd\/swift\/bool\/init(_:)-5q3cx","role":"symbol","identifier":"doc:\/\/SwiftUsd\/documentation\/OpenUSD\/Swift\/Bool\/init(_:)-5q3cx","fragments":[{"text":"init","kind":"identifier"},{"text":"(","kind":"text"},{"text":"some","kind":"keyword"},{"text":" ","kind":"text"},{"preciseIdentifier":"c:@N@Overlay","text":"Overlay","kind":"typeIdentifier"},{"text":".","kind":"text"},{"preciseIdentifier":"s:So7OverlayO7OpenUSDE23_TfConstWeakPtrProtocolP","text":"_TfConstWeakPtrProtocol","kind":"typeIdentifier"},{"text":")","kind":"text"}],"type":"topic"},"doc://SwiftUsd/documentation/OpenUSD/Swift/Bool/init(_:)-54yuh":{"title":"init(_:)","url":"\/documentation\/openusd\/swift\/bool\/init(_:)-54yuh","fragments":[{"text":"init","kind":"identifier"},{"text":"(","kind":"text"},{"preciseIdentifier":"s:7OpenUSD3pxra","text":"pxr","kind":"typeIdentifier"},{"text":".","kind":"text"},{"preciseIdentifier":"c:@N@pxr@S@UsdObject","text":"UsdObject","kind":"typeIdentifier"},{"text":")","kind":"text"}],"abstract":[{"type":"text","text":"Returns "},{"code":"true","type":"codeVoice"},{"type":"text","text":" if the "},{"code":"UsdObject","type":"codeVoice"},{"type":"text","text":" is valid"}],"role":"symbol","kind":"symbol","identifier":"doc:\/\/SwiftUsd\/documentation\/OpenUSD\/Swift\/Bool\/init(_:)-54yuh","type":"topic"},"doc://SwiftUsd/documentation/OpenUSD/Swift/Bool/init(_:)-115q0":{"type":"topic","abstract":[],"url":"\/documentation\/openusd\/swift\/bool\/init(_:)-115q0","fragments":[{"kind":"identifier","text":"init"},{"kind":"text","text":"("},{"preciseIdentifier":"s:7OpenUSD3pxra","kind":"typeIdentifier","text":"pxr"},{"kind":"text","text":"."},{"preciseIdentifier":"c:@N@pxr@S@UsdLuxPluginLight","kind":"typeIdentifier","text":"UsdLuxPluginLight"},{"kind":"text","text":")"}],"kind":"symbol","identifier":"doc:\/\/SwiftUsd\/documentation\/OpenUSD\/Swift\/Bool\/init(_:)-115q0","role":"symbol","title":"init(_:)"},"doc://SwiftUsd/documentation/OpenUSD/Swift/Bool/init(_:)-8q9wj":{"url":"\/documentation\/openusd\/swift\/bool\/init(_:)-8q9wj","identifier":"doc:\/\/SwiftUsd\/documentation\/OpenUSD\/Swift\/Bool\/init(_:)-8q9wj","fragments":[{"text":"init","kind":"identifier"},{"text":"(","kind":"text"},{"preciseIdentifier":"s:7OpenUSD3pxra","text":"pxr","kind":"typeIdentifier"},{"text":".","kind":"text"},{"preciseIdentifier":"c:@N@pxr@S@UsdModelAPI","text":"UsdModelAPI","kind":"typeIdentifier"},{"text":")","kind":"text"}],"abstract":[],"kind":"symbol","role":"symbol","title":"init(_:)","type":"topic"},"doc://SwiftUsd/documentation/OpenUSD/Swift/Bool/init(_:)-8zcdx":{"url":"\/documentation\/openusd\/swift\/bool\/init(_:)-8zcdx","identifier":"doc:\/\/SwiftUsd\/documentation\/OpenUSD\/Swift\/Bool\/init(_:)-8zcdx","abstract":[],"type":"topic","kind":"symbol","title":"init(_:)","role":"symbol","fragments":[{"text":"init","kind":"identifier"},{"text":"(","kind":"text"},{"preciseIdentifier":"s:7OpenUSD3pxra","text":"pxr","kind":"typeIdentifier"},{"text":".","kind":"text"},{"preciseIdentifier":"c:@N@pxr@S@UsdLuxMeshLightAPI","text":"UsdLuxMeshLightAPI","kind":"typeIdentifier"},{"text":")","kind":"text"}]},"doc://SwiftUsd/documentation/OpenUSD/Swift/Bool/init(_:)-2ioqb":{"title":"init(_:)","url":"\/documentation\/openusd\/swift\/bool\/init(_:)-2ioqb","fragments":[{"text":"init","kind":"identifier"},{"text":"(","kind":"text"},{"preciseIdentifier":"s:7OpenUSD3pxra","text":"pxr","kind":"typeIdentifier"},{"text":".","kind":"text"},{"preciseIdentifier":"c:@N@pxr@S@UsdSkelAnimation","text":"UsdSkelAnimation","kind":"typeIdentifier"},{"text":")","kind":"text"}],"abstract":[],"role":"symbol","kind":"symbol","identifier":"doc:\/\/SwiftUsd\/documentation\/OpenUSD\/Swift\/Bool\/init(_:)-2ioqb","type":"topic"},"doc://SwiftUsd/documentation/OpenUSD/Swift/Bool/init(_:)-65z1v":{"title":"init(_:)","url":"\/documentation\/openusd\/swift\/bool\/init(_:)-65z1v","fragments":[{"text":"init","kind":"identifier"},{"text":"(","kind":"text"},{"preciseIdentifier":"s:7OpenUSD3pxra","text":"pxr","kind":"typeIdentifier"},{"text":".","kind":"text"},{"preciseIdentifier":"c:@N@pxr@S@UsdPhysicsCollisionGroup","text":"UsdPhysicsCollisionGroup","kind":"typeIdentifier"},{"text":")","kind":"text"}],"abstract":[],"role":"symbol","kind":"symbol","identifier":"doc:\/\/SwiftUsd\/documentation\/OpenUSD\/Swift\/Bool\/init(_:)-65z1v","type":"topic"},"doc://SwiftUsd/documentation/OpenUSD/Swift/Bool/init(_:)-5t6d7":{"title":"init(_:)","type":"topic","kind":"symbol","identifier":"doc:\/\/SwiftUsd\/documentation\/OpenUSD\/Swift\/Bool\/init(_:)-5t6d7","fragments":[{"text":"init","kind":"identifier"},{"text":"(","kind":"text"},{"preciseIdentifier":"s:7OpenUSD3pxra","text":"pxr","kind":"typeIdentifier"},{"text":".","kind":"text"},{"preciseIdentifier":"c:@N@pxr@S@UsdSkelRoot","text":"UsdSkelRoot","kind":"typeIdentifier"},{"text":")","kind":"text"}],"role":"symbol","url":"\/documentation\/openusd\/swift\/bool\/init(_:)-5t6d7","abstract":[]},"doc://SwiftUsd/documentation/OpenUSD/Swift/Bool/init(_:)-8fpmu":{"kind":"symbol","fragments":[{"text":"init","kind":"identifier"},{"text":"(","kind":"text"},{"preciseIdentifier":"s:7OpenUSD3pxra","text":"pxr","kind":"typeIdentifier"},{"text":".","kind":"text"},{"preciseIdentifier":"c:@N@pxr@S@UsdPhysicsPrismaticJoint","text":"UsdPhysicsPrismaticJoint","kind":"typeIdentifier"},{"text":")","kind":"text"}],"url":"\/documentation\/openusd\/swift\/bool\/init(_:)-8fpmu","role":"symbol","type":"topic","identifier":"doc:\/\/SwiftUsd\/documentation\/OpenUSD\/Swift\/Bool\/init(_:)-8fpmu","abstract":[],"title":"init(_:)"},"doc://SwiftUsd/documentation/OpenUSD/Swift/Bool/init(_:)-8booq":{"kind":"symbol","identifier":"doc:\/\/SwiftUsd\/documentation\/OpenUSD\/Swift\/Bool\/init(_:)-8booq","fragments":[{"text":"init","kind":"identifier"},{"text":"(","kind":"text"},{"preciseIdentifier":"s:7OpenUSD3pxra","text":"pxr","kind":"typeIdentifier"},{"text":".","kind":"text"},{"preciseIdentifier":"c:@N@pxr@S@UsdGeomXformable","text":"UsdGeomXformable","kind":"typeIdentifier"},{"text":")","kind":"text"}],"role":"symbol","url":"\/documentation\/openusd\/swift\/bool\/init(_:)-8booq","title":"init(_:)","type":"topic","abstract":[]},"doc://SwiftUsd/documentation/OpenUSD/Swift/Bool/init(_:)-3o5k":{"identifier":"doc:\/\/SwiftUsd\/documentation\/OpenUSD\/Swift\/Bool\/init(_:)-3o5k","type":"topic","abstract":[{"type":"text","text":"Returns "},{"code":"true","type":"codeVoice"},{"type":"text","text":" is the spec has not expired"}],"role":"symbol","url":"\/documentation\/openusd\/swift\/bool\/init(_:)-3o5k","kind":"symbol","title":"init(_:)","fragments":[{"text":"init","kind":"identifier"},{"text":"(","kind":"text"},{"preciseIdentifier":"s:7OpenUSD3pxra","text":"pxr","kind":"typeIdentifier"},{"text":".","kind":"text"},{"preciseIdentifier":"c:types.h@N@pxr@T@SdfSpecHandle","text":"SdfSpecHandle","kind":"typeIdentifier"},{"text":")","kind":"text"}]},"doc://SwiftUsd/documentation/OpenUSD/Swift/Bool/init(_:)-2gm7u":{"abstract":[],"title":"init(_:)","identifier":"doc:\/\/SwiftUsd\/documentation\/OpenUSD\/Swift\/Bool\/init(_:)-2gm7u","role":"symbol","fragments":[{"text":"init","kind":"identifier"},{"text":"(","kind":"text"},{"preciseIdentifier":"s:7OpenUSD3pxra","text":"pxr","kind":"typeIdentifier"},{"text":".","kind":"text"},{"preciseIdentifier":"c:@N@pxr@S@UsdGeomModelAPI","text":"UsdGeomModelAPI","kind":"typeIdentifier"},{"text":")","kind":"text"}],"type":"topic","url":"\/documentation\/openusd\/swift\/bool\/init(_:)-2gm7u","kind":"symbol"},"doc://SwiftUsd/documentation/OpenUSD/Swift/Bool/init(_:)-5oibg":{"kind":"symbol","url":"\/documentation\/openusd\/swift\/bool\/init(_:)-5oibg","abstract":[],"fragments":[{"text":"init","kind":"identifier"},{"text":"(","kind":"text"},{"preciseIdentifier":"s:7OpenUSD3pxra","text":"pxr","kind":"typeIdentifier"},{"text":".","kind":"text"},{"preciseIdentifier":"c:@N@pxr@S@UsdSkelSkeleton","text":"UsdSkelSkeleton","kind":"typeIdentifier"},{"text":")","kind":"text"}],"identifier":"doc:\/\/SwiftUsd\/documentation\/OpenUSD\/Swift\/Bool\/init(_:)-5oibg","type":"topic","role":"symbol","title":"init(_:)"},"doc://SwiftUsd/documentation/OpenUSD/Swift/Bool/init(_:)-qehe":{"identifier":"doc:\/\/SwiftUsd\/documentation\/OpenUSD\/Swift\/Bool\/init(_:)-qehe","type":"topic","role":"symbol","kind":"symbol","url":"\/documentation\/openusd\/swift\/bool\/init(_:)-qehe","title":"init(_:)","fragments":[{"text":"init","kind":"identifier"},{"text":"(","kind":"text"},{"preciseIdentifier":"s:7OpenUSD3pxra","text":"pxr","kind":"typeIdentifier"},{"text":".","kind":"text"},{"preciseIdentifier":"c:@N@pxr@S@UsdGeomHermiteCurves","text":"UsdGeomHermiteCurves","kind":"typeIdentifier"},{"text":")","kind":"text"}],"abstract":[]},"doc://SwiftUsd/documentation/OpenUSD/Swift/Bool/init(_:)-6v4k8":{"role":"symbol","url":"\/documentation\/openusd\/swift\/bool\/init(_:)-6v4k8","title":"init(_:)","kind":"symbol","type":"topic","identifier":"doc:\/\/SwiftUsd\/documentation\/OpenUSD\/Swift\/Bool\/init(_:)-6v4k8","fragments":[{"text":"init","kind":"identifier"},{"text":"(","kind":"text"},{"preciseIdentifier":"s:7OpenUSD3pxra","text":"pxr","kind":"typeIdentifier"},{"text":".","kind":"text"},{"preciseIdentifier":"c:@N@pxr@S@UsdShadeOutput","text":"UsdShadeOutput","kind":"typeIdentifier"},{"text":")","kind":"text"}],"abstract":[{"type":"text","text":"Returns "},{"code":"true","type":"codeVoice"},{"type":"text","text":" if the "},{"code":"UsdShadeOutput","type":"codeVoice"},{"type":"text","text":" is valid"}]},"doc://SwiftUsd/documentation/OpenUSD/Swift/Bool/init(_:)-5fp8":{"abstract":[],"fragments":[{"text":"init","kind":"identifier"},{"text":"(","kind":"text"},{"preciseIdentifier":"s:7OpenUSD3pxra","text":"pxr","kind":"typeIdentifier"},{"text":".","kind":"text"},{"preciseIdentifier":"c:@N@pxr@S@UsdGeomTetMesh","text":"UsdGeomTetMesh","kind":"typeIdentifier"},{"text":")","kind":"text"}],"title":"init(_:)","url":"\/documentation\/openusd\/swift\/bool\/init(_:)-5fp8","type":"topic","kind":"symbol","identifier":"doc:\/\/SwiftUsd\/documentation\/OpenUSD\/Swift\/Bool\/init(_:)-5fp8","role":"symbol"},"doc://SwiftUsd/documentation/OpenUSD/Swift/Bool/init(_:)-7f7t0":{"title":"init(_:)","kind":"symbol","identifier":"doc:\/\/SwiftUsd\/documentation\/OpenUSD\/Swift\/Bool\/init(_:)-7f7t0","url":"\/documentation\/openusd\/swift\/bool\/init(_:)-7f7t0","type":"topic","role":"symbol","abstract":[],"fragments":[{"text":"init","kind":"identifier"},{"text":"(","kind":"text"},{"preciseIdentifier":"s:7OpenUSD3pxra","text":"pxr","kind":"typeIdentifier"},{"text":".","kind":"text"},{"preciseIdentifier":"c:@N@pxr@S@UsdGeomCube","text":"UsdGeomCube","kind":"typeIdentifier"},{"text":")","kind":"text"}]},"doc://SwiftUsd/documentation/OpenUSD/Swift/Bool/init(_:)-2sprp":{"fragments":[{"text":"init","kind":"identifier"},{"text":"(","kind":"text"},{"preciseIdentifier":"s:7OpenUSD3pxra","text":"pxr","kind":"typeIdentifier"},{"text":".","kind":"text"},{"preciseIdentifier":"c:@N@pxr@S@UsdGeomCone","text":"UsdGeomCone","kind":"typeIdentifier"},{"text":")","kind":"text"}],"title":"init(_:)","abstract":[],"url":"\/documentation\/openusd\/swift\/bool\/init(_:)-2sprp","type":"topic","role":"symbol","identifier":"doc:\/\/SwiftUsd\/documentation\/OpenUSD\/Swift\/Bool\/init(_:)-2sprp","kind":"symbol"},"doc://SwiftUsd/documentation/OpenUSD/Swift/Bool/init(_:)-83d6l":{"url":"\/documentation\/openusd\/swift\/bool\/init(_:)-83d6l","role":"symbol","kind":"symbol","identifier":"doc:\/\/SwiftUsd\/documentation\/OpenUSD\/Swift\/Bool\/init(_:)-83d6l","type":"topic","abstract":[],"fragments":[{"text":"init","kind":"identifier"},{"text":"(","kind":"text"},{"preciseIdentifier":"s:7OpenUSD3pxra","text":"pxr","kind":"typeIdentifier"},{"text":".","kind":"text"},{"preciseIdentifier":"c:@N@pxr@S@UsdGeomPlane","text":"UsdGeomPlane","kind":"typeIdentifier"},{"text":")","kind":"text"}],"title":"init(_:)"},"doc://SwiftUsd/documentation/OpenUSD/Swift/Bool/init(_:)-59grs":{"kind":"symbol","url":"\/documentation\/openusd\/swift\/bool\/init(_:)-59grs","identifier":"doc:\/\/SwiftUsd\/documentation\/OpenUSD\/Swift\/Bool\/init(_:)-59grs","type":"topic","fragments":[{"text":"init","kind":"identifier"},{"text":"(","kind":"text"},{"preciseIdentifier":"s:7OpenUSD3pxra","text":"pxr","kind":"typeIdentifier"},{"text":".","kind":"text"},{"preciseIdentifier":"c:@N@pxr@S@UsdShadeInput","text":"UsdShadeInput","kind":"typeIdentifier"},{"text":")","kind":"text"}],"title":"init(_:)","abstract":[{"type":"text","text":"Returns "},{"type":"codeVoice","code":"true"},{"type":"text","text":" if the "},{"type":"codeVoice","code":"UsdShadeInput"},{"type":"text","text":" is valid"}],"role":"symbol"},"doc://SwiftUsd/documentation/OpenUSD/Swift/Bool/init(_:)-6f2qs":{"role":"symbol","url":"\/documentation\/openusd\/swift\/bool\/init(_:)-6f2qs","type":"topic","fragments":[{"text":"init","kind":"identifier"},{"text":"(","kind":"text"},{"preciseIdentifier":"s:7OpenUSD3pxra","text":"pxr","kind":"typeIdentifier"},{"text":".","kind":"text"},{"preciseIdentifier":"c:@N@pxr@S@UsdProperty","text":"UsdProperty","kind":"typeIdentifier"},{"text":")","kind":"text"}],"kind":"symbol","identifier":"doc:\/\/SwiftUsd\/documentation\/OpenUSD\/Swift\/Bool\/init(_:)-6f2qs","title":"init(_:)","abstract":[{"type":"text","text":"Returns "},{"code":"true","type":"codeVoice"},{"type":"text","text":" if the "},{"code":"UsdProperty","type":"codeVoice"},{"type":"text","text":" is valid"}]},"doc://SwiftUsd/documentation/OpenUSD/Swift/Bool/init(_:)-4n62a":{"url":"\/documentation\/openusd\/swift\/bool\/init(_:)-4n62a","abstract":[],"type":"topic","role":"symbol","fragments":[{"text":"init","kind":"identifier"},{"text":"(","kind":"text"},{"preciseIdentifier":"s:7OpenUSD3pxra","text":"pxr","kind":"typeIdentifier"},{"text":".","kind":"text"},{"preciseIdentifier":"c:@N@pxr@S@UsdPhysicsSphericalJoint","text":"UsdPhysicsSphericalJoint","kind":"typeIdentifier"},{"text":")","kind":"text"}],"title":"init(_:)","identifier":"doc:\/\/SwiftUsd\/documentation\/OpenUSD\/Swift\/Bool\/init(_:)-4n62a","kind":"symbol"},"doc://SwiftUsd/documentation/OpenUSD/Swift/Bool/init(_:)-6pmx3":{"kind":"symbol","url":"\/documentation\/openusd\/swift\/bool\/init(_:)-6pmx3","identifier":"doc:\/\/SwiftUsd\/documentation\/OpenUSD\/Swift\/Bool\/init(_:)-6pmx3","type":"topic","fragments":[{"text":"init","kind":"identifier"},{"text":"(","kind":"text"},{"preciseIdentifier":"s:7OpenUSD3pxra","text":"pxr","kind":"typeIdentifier"},{"text":".","kind":"text"},{"preciseIdentifier":"c:@N@pxr@S@UsdLuxShapingAPI","text":"UsdLuxShapingAPI","kind":"typeIdentifier"},{"text":")","kind":"text"}],"title":"init(_:)","abstract":[],"role":"symbol"},"doc://SwiftUsd/documentation/OpenUSD/Swift/Bool/init(_:)-1luc0":{"identifier":"doc:\/\/SwiftUsd\/documentation\/OpenUSD\/Swift\/Bool\/init(_:)-1luc0","role":"symbol","title":"init(_:)","kind":"symbol","url":"\/documentation\/openusd\/swift\/bool\/init(_:)-1luc0","abstract":[],"type":"topic","fragments":[{"text":"init","kind":"identifier"},{"text":"(","kind":"text"},{"preciseIdentifier":"s:7OpenUSD3pxra","text":"pxr","kind":"typeIdentifier"},{"text":".","kind":"text"},{"preciseIdentifier":"c:@N@pxr@S@UsdShadeShader","text":"UsdShadeShader","kind":"typeIdentifier"},{"text":")","kind":"text"}]},"doc://SwiftUsd/documentation/OpenUSD/Swift/Bool/init(_:)-6mx0i":{"url":"\/documentation\/openusd\/swift\/bool\/init(_:)-6mx0i","role":"symbol","type":"topic","title":"init(_:)","kind":"symbol","fragments":[{"text":"init","kind":"identifier"},{"text":"(","kind":"text"},{"preciseIdentifier":"s:7OpenUSD3pxra","text":"pxr","kind":"typeIdentifier"},{"text":".","kind":"text"},{"preciseIdentifier":"c:@N@pxr@S@UsdGeomGprim","text":"UsdGeomGprim","kind":"typeIdentifier"},{"text":")","kind":"text"}],"identifier":"doc:\/\/SwiftUsd\/documentation\/OpenUSD\/Swift\/Bool\/init(_:)-6mx0i","abstract":[]},"doc://SwiftUsd/documentation/OpenUSD":{"title":"OpenUSD","url":"\/documentation\/openusd","kind":"symbol","identifier":"doc:\/\/SwiftUsd\/documentation\/OpenUSD","role":"collection","abstract":[],"type":"topic"},"doc://SwiftUsd/documentation/OpenUSD/Swift/Bool/init(_:)-1r04v":{"type":"topic","role":"symbol","abstract":[],"identifier":"doc:\/\/SwiftUsd\/documentation\/OpenUSD\/Swift\/Bool\/init(_:)-1r04v","title":"init(_:)","fragments":[{"text":"init","kind":"identifier"},{"text":"(","kind":"text"},{"preciseIdentifier":"s:7OpenUSD3pxra","text":"pxr","kind":"typeIdentifier"},{"text":".","kind":"text"},{"preciseIdentifier":"c:@N@pxr@S@UsdPhysicsMassAPI","text":"UsdPhysicsMassAPI","kind":"typeIdentifier"},{"text":")","kind":"text"}],"kind":"symbol","url":"\/documentation\/openusd\/swift\/bool\/init(_:)-1r04v"},"doc://SwiftUsd/documentation/OpenUSD/Swift/Bool/init(_:)-5qdkk":{"role":"symbol","kind":"symbol","url":"\/documentation\/openusd\/swift\/bool\/init(_:)-5qdkk","identifier":"doc:\/\/SwiftUsd\/documentation\/OpenUSD\/Swift\/Bool\/init(_:)-5qdkk","fragments":[{"text":"init","kind":"identifier"},{"text":"(","kind":"text"},{"preciseIdentifier":"s:7OpenUSD3pxra","text":"pxr","kind":"typeIdentifier"},{"text":".","kind":"text"},{"preciseIdentifier":"c:@N@pxr@S@UsdGeomCylinder","text":"UsdGeomCylinder","kind":"typeIdentifier"},{"text":")","kind":"text"}],"type":"topic","abstract":[],"title":"init(_:)"},"doc://SwiftUsd/documentation/OpenUSD/Swift/Bool/init(_:)-4o3dw":{"fragments":[{"text":"init","kind":"identifier"},{"text":"(","kind":"text"},{"preciseIdentifier":"s:7OpenUSD3pxra","text":"pxr","kind":"typeIdentifier"},{"text":".","kind":"text"},{"preciseIdentifier":"c:@N@pxr@S@UsdGeomCurves","text":"UsdGeomCurves","kind":"typeIdentifier"},{"text":")","kind":"text"}],"role":"symbol","type":"topic","kind":"symbol","identifier":"doc:\/\/SwiftUsd\/documentation\/OpenUSD\/Swift\/Bool\/init(_:)-4o3dw","url":"\/documentation\/openusd\/swift\/bool\/init(_:)-4o3dw","title":"init(_:)","abstract":[]},"doc://SwiftUsd/documentation/OpenUSD/Swift/Bool/init(_:)-6b8vj":{"type":"topic","identifier":"doc:\/\/SwiftUsd\/documentation\/OpenUSD\/Swift\/Bool\/init(_:)-6b8vj","kind":"symbol","url":"\/documentation\/openusd\/swift\/bool\/init(_:)-6b8vj","title":"init(_:)","fragments":[{"text":"init","kind":"identifier"},{"text":"(","kind":"text"},{"preciseIdentifier":"s:7OpenUSD3pxra","text":"pxr","kind":"typeIdentifier"},{"text":".","kind":"text"},{"preciseIdentifier":"c:@N@pxr@S@UsdPhysicsFilteredPairsAPI","text":"UsdPhysicsFilteredPairsAPI","kind":"typeIdentifier"},{"text":")","kind":"text"}],"abstract":[],"role":"symbol"},"doc://SwiftUsd/documentation/OpenUSD/Swift/Bool/init(_:)-3nlk2":{"kind":"symbol","title":"init(_:)","abstract":[],"type":"topic","fragments":[{"text":"init","kind":"identifier"},{"text":"(","kind":"text"},{"preciseIdentifier":"s:7OpenUSD3pxra","text":"pxr","kind":"typeIdentifier"},{"text":".","kind":"text"},{"preciseIdentifier":"c:@N@pxr@S@UsdUISceneGraphPrimAPI","text":"UsdUISceneGraphPrimAPI","kind":"typeIdentifier"},{"text":")","kind":"text"}],"role":"symbol","identifier":"doc:\/\/SwiftUsd\/documentation\/OpenUSD\/Swift\/Bool\/init(_:)-3nlk2","url":"\/documentation\/openusd\/swift\/bool\/init(_:)-3nlk2"},"doc://SwiftUsd/documentation/OpenUSD/Swift/Bool/init(_:)-8lpgx":{"identifier":"doc:\/\/SwiftUsd\/documentation\/OpenUSD\/Swift\/Bool\/init(_:)-8lpgx","role":"symbol","type":"topic","url":"\/documentation\/openusd\/swift\/bool\/init(_:)-8lpgx","kind":"symbol","title":"init(_:)","fragments":[{"text":"init","kind":"identifier"},{"text":"(","kind":"text"},{"text":"some","kind":"keyword"},{"text":" ","kind":"text"},{"preciseIdentifier":"c:@N@Overlay","text":"Overlay","kind":"typeIdentifier"},{"text":".","kind":"text"},{"preciseIdentifier":"s:So7OverlayO7OpenUSDE22_TfConstRefPtrProtocolP","text":"_TfConstRefPtrProtocol","kind":"typeIdentifier"},{"text":")","kind":"text"}],"abstract":[{"type":"text","text":"Returns "},{"code":"true","type":"codeVoice"},{"type":"text","text":" if the pointer is not null"}]},"doc://SwiftUsd/documentation/OpenUSD/Swift/Bool/init(_:)-3b5qw":{"type":"topic","url":"\/documentation\/openusd\/swift\/bool\/init(_:)-3b5qw","abstract":[],"fragments":[{"text":"init","kind":"identifier"},{"text":"(","kind":"text"},{"preciseIdentifier":"s:7OpenUSD3pxra","text":"pxr","kind":"typeIdentifier"},{"text":".","kind":"text"},{"preciseIdentifier":"c:@N@pxr@S@UsdPhysicsRevoluteJoint","text":"UsdPhysicsRevoluteJoint","kind":"typeIdentifier"},{"text":")","kind":"text"}],"title":"init(_:)","identifier":"doc:\/\/SwiftUsd\/documentation\/OpenUSD\/Swift\/Bool\/init(_:)-3b5qw","kind":"symbol","role":"symbol"},"doc://SwiftUsd/documentation/OpenUSD/Swift/Bool/init(_:)-1y5uh":{"abstract":[],"title":"init(_:)","url":"\/documentation\/openusd\/swift\/bool\/init(_:)-1y5uh","role":"symbol","type":"topic","kind":"symbol","identifier":"doc:\/\/SwiftUsd\/documentation\/OpenUSD\/Swift\/Bool\/init(_:)-1y5uh","fragments":[{"text":"init","kind":"identifier"},{"text":"(","kind":"text"},{"preciseIdentifier":"s:7OpenUSD3pxra","text":"pxr","kind":"typeIdentifier"},{"text":".","kind":"text"},{"preciseIdentifier":"c:@N@pxr@S@UsdGeomMotionAPI","text":"UsdGeomMotionAPI","kind":"typeIdentifier"},{"text":")","kind":"text"}]},"doc://SwiftUsd/documentation/OpenUSD/Swift/Bool/init(_:)-1qrd5":{"kind":"symbol","title":"init(_:)","identifier":"doc:\/\/SwiftUsd\/documentation\/OpenUSD\/Swift\/Bool\/init(_:)-1qrd5","abstract":[],"type":"topic","role":"symbol","fragments":[{"text":"init","kind":"identifier"},{"text":"(","kind":"text"},{"preciseIdentifier":"s:7OpenUSD3pxra","text":"pxr","kind":"typeIdentifier"},{"text":".","kind":"text"},{"preciseIdentifier":"c:@N@pxr@S@UsdGeomNurbsCurves","text":"UsdGeomNurbsCurves","kind":"typeIdentifier"},{"text":")","kind":"text"}],"url":"\/documentation\/openusd\/swift\/bool\/init(_:)-1qrd5"},"doc://SwiftUsd/documentation/OpenUSD/Swift/Bool/init(_:)-9h3j9":{"type":"topic","url":"\/documentation\/openusd\/swift\/bool\/init(_:)-9h3j9","kind":"symbol","title":"init(_:)","role":"symbol","identifier":"doc:\/\/SwiftUsd\/documentation\/OpenUSD\/Swift\/Bool\/init(_:)-9h3j9","abstract":[],"fragments":[{"text":"init","kind":"identifier"},{"text":"(","kind":"text"},{"preciseIdentifier":"s:7OpenUSD3pxra","text":"pxr","kind":"typeIdentifier"},{"text":".","kind":"text"},{"preciseIdentifier":"c:@N@pxr@S@UsdLuxBoundableLightBase","text":"UsdLuxBoundableLightBase","kind":"typeIdentifier"},{"text":")","kind":"text"}]},"doc://SwiftUsd/documentation/OpenUSD/Swift/Bool/init(_:)-4pu1o":{"title":"init(_:)","type":"topic","url":"\/documentation\/openusd\/swift\/bool\/init(_:)-4pu1o","kind":"symbol","fragments":[{"text":"init","kind":"identifier"},{"text":"(","kind":"text"},{"preciseIdentifier":"s:7OpenUSD3pxra","text":"pxr","kind":"typeIdentifier"},{"text":".","kind":"text"},{"preciseIdentifier":"c:types.h@N@pxr@T@SdfAttributeSpecHandle","text":"SdfAttributeSpecHandle","kind":"typeIdentifier"},{"text":")","kind":"text"}],"abstract":[{"type":"text","text":"Returns "},{"type":"codeVoice","code":"true"},{"type":"text","text":" is the spec has not expired"}],"role":"symbol","identifier":"doc:\/\/SwiftUsd\/documentation\/OpenUSD\/Swift\/Bool\/init(_:)-4pu1o"},"doc://SwiftUsd/documentation/OpenUSD/Swift/Bool/init(_:)-7lr0x":{"identifier":"doc:\/\/SwiftUsd\/documentation\/OpenUSD\/Swift\/Bool\/init(_:)-7lr0x","type":"topic","fragments":[{"text":"init","kind":"identifier"},{"text":"(","kind":"text"},{"preciseIdentifier":"s:7OpenUSD3pxra","text":"pxr","kind":"typeIdentifier"},{"text":".","kind":"text"},{"preciseIdentifier":"c:@N@pxr@S@UsdProcGenerativeProcedural","text":"UsdProcGenerativeProcedural","kind":"typeIdentifier"},{"text":")","kind":"text"}],"role":"symbol","url":"\/documentation\/openusd\/swift\/bool\/init(_:)-7lr0x","title":"init(_:)","abstract":[],"kind":"symbol"},"doc://SwiftUsd/documentation/OpenUSD/Swift/Bool/init(_:)-4kvqu":{"identifier":"doc:\/\/SwiftUsd\/documentation\/OpenUSD\/Swift\/Bool\/init(_:)-4kvqu","abstract":[],"kind":"symbol","fragments":[{"text":"init","kind":"identifier"},{"text":"(","kind":"text"},{"preciseIdentifier":"s:7OpenUSD3pxra","text":"pxr","kind":"typeIdentifier"},{"text":".","kind":"text"},{"preciseIdentifier":"c:@N@pxr@S@UsdVolFieldBase","text":"UsdVolFieldBase","kind":"typeIdentifier"},{"text":")","kind":"text"}],"role":"symbol","url":"\/documentation\/openusd\/swift\/bool\/init(_:)-4kvqu","type":"topic","title":"init(_:)"},"doc://SwiftUsd/documentation/OpenUSD/Swift/Bool/init(_:)-7maed":{"kind":"symbol","url":"\/documentation\/openusd\/swift\/bool\/init(_:)-7maed","abstract":[],"role":"symbol","title":"init(_:)","identifier":"doc:\/\/SwiftUsd\/documentation\/OpenUSD\/Swift\/Bool\/init(_:)-7maed","fragments":[{"text":"init","kind":"identifier"},{"text":"(","kind":"text"},{"preciseIdentifier":"s:7OpenUSD3pxra","text":"pxr","kind":"typeIdentifier"},{"text":".","kind":"text"},{"preciseIdentifier":"c:@N@pxr@S@UsdSkelBlendShape","text":"UsdSkelBlendShape","kind":"typeIdentifier"},{"text":")","kind":"text"}],"type":"topic"},"doc://SwiftUsd/documentation/OpenUSD/Swift/Bool/init(_:)-1mj2o":{"role":"symbol","url":"\/documentation\/openusd\/swift\/bool\/init(_:)-1mj2o","title":"init(_:)","fragments":[{"text":"init","kind":"identifier"},{"text":"(","kind":"text"},{"preciseIdentifier":"s:7OpenUSD3pxra","text":"pxr","kind":"typeIdentifier"},{"text":".","kind":"text"},{"preciseIdentifier":"c:@N@pxr@S@UsdPhysicsLimitAPI","text":"UsdPhysicsLimitAPI","kind":"typeIdentifier"},{"text":")","kind":"text"}],"identifier":"doc:\/\/SwiftUsd\/documentation\/OpenUSD\/Swift\/Bool\/init(_:)-1mj2o","abstract":[],"kind":"symbol","type":"topic"},"doc://SwiftUsd/documentation/OpenUSD/Swift/Bool/init(_:)-7p9wz":{"kind":"symbol","type":"topic","role":"symbol","url":"\/documentation\/openusd\/swift\/bool\/init(_:)-7p9wz","title":"init(_:)","abstract":[],"identifier":"doc:\/\/SwiftUsd\/documentation\/OpenUSD\/Swift\/Bool\/init(_:)-7p9wz","fragments":[{"text":"init","kind":"identifier"},{"text":"(","kind":"text"},{"preciseIdentifier":"s:7OpenUSD3pxra","text":"pxr","kind":"typeIdentifier"},{"text":".","kind":"text"},{"preciseIdentifier":"c:@N@pxr@S@UsdGeomXformCommonAPI","text":"UsdGeomXformCommonAPI","kind":"typeIdentifier"},{"text":")","kind":"text"}]},"doc://SwiftUsd/documentation/OpenUSD/Swift/Bool/init(_:)-2mlpg":{"type":"topic","role":"symbol","identifier":"doc:\/\/SwiftUsd\/documentation\/OpenUSD\/Swift\/Bool\/init(_:)-2mlpg","url":"\/documentation\/openusd\/swift\/bool\/init(_:)-2mlpg","fragments":[{"text":"init","kind":"identifier"},{"text":"(","kind":"text"},{"preciseIdentifier":"s:7OpenUSD3pxra","text":"pxr","kind":"typeIdentifier"},{"text":".","kind":"text"},{"preciseIdentifier":"c:@N@pxr@S@UsdLuxSphereLight","text":"UsdLuxSphereLight","kind":"typeIdentifier"},{"text":")","kind":"text"}],"abstract":[],"kind":"symbol","title":"init(_:)"},"doc://SwiftUsd/documentation/OpenUSD/Swift/Bool/init(_:)-7itb6":{"type":"topic","role":"symbol","identifier":"doc:\/\/SwiftUsd\/documentation\/OpenUSD\/Swift\/Bool\/init(_:)-7itb6","url":"\/documentation\/openusd\/swift\/bool\/init(_:)-7itb6","fragments":[{"text":"init","kind":"identifier"},{"text":"(","kind":"text"},{"preciseIdentifier":"s:7OpenUSD3pxra","text":"pxr","kind":"typeIdentifier"},{"text":".","kind":"text"},{"preciseIdentifier":"c:@N@pxr@S@UsdGeomBasisCurves","text":"UsdGeomBasisCurves","kind":"typeIdentifier"},{"text":")","kind":"text"}],"abstract":[],"kind":"symbol","title":"init(_:)"},"doc://SwiftUsd/documentation/OpenUSD/Swift/Bool/init(_:)-9ekuz":{"kind":"symbol","abstract":[],"url":"\/documentation\/openusd\/swift\/bool\/init(_:)-9ekuz","role":"symbol","identifier":"doc:\/\/SwiftUsd\/documentation\/OpenUSD\/Swift\/Bool\/init(_:)-9ekuz","fragments":[{"text":"init","kind":"identifier"},{"text":"(","kind":"text"},{"preciseIdentifier":"s:7OpenUSD3pxra","text":"pxr","kind":"typeIdentifier"},{"text":".","kind":"text"},{"preciseIdentifier":"c:@N@pxr@S@UsdLuxDistantLight","text":"UsdLuxDistantLight","kind":"typeIdentifier"},{"text":")","kind":"text"}],"title":"init(_:)","type":"topic"},"doc://SwiftUsd/documentation/OpenUSD/Swift/Bool/init(_:)-91yiw":{"url":"\/documentation\/openusd\/swift\/bool\/init(_:)-91yiw","identifier":"doc:\/\/SwiftUsd\/documentation\/OpenUSD\/Swift\/Bool\/init(_:)-91yiw","abstract":[{"type":"text","text":"Returns "},{"code":"true","type":"codeVoice"},{"type":"text","text":" if the zip file is valid"}],"type":"topic","kind":"symbol","role":"symbol","fragments":[{"text":"init","kind":"identifier"},{"text":"(","kind":"text"},{"preciseIdentifier":"s:7OpenUSD3pxra","text":"pxr","kind":"typeIdentifier"},{"text":".","kind":"text"},{"preciseIdentifier":"c:@N@pxr@UsdZipFile","text":"UsdZipFile","kind":"typeIdentifier"},{"text":")","kind":"text"}],"title":"init(_:)"},"doc://SwiftUsd/documentation/OpenUSD/Swift/Bool/init(_:)-8fpc0":{"kind":"symbol","type":"topic","role":"symbol","url":"\/documentation\/openusd\/swift\/bool\/init(_:)-8fpc0","title":"init(_:)","abstract":[],"identifier":"doc:\/\/SwiftUsd\/documentation\/OpenUSD\/Swift\/Bool\/init(_:)-8fpc0","fragments":[{"text":"init","kind":"identifier"},{"text":"(","kind":"text"},{"preciseIdentifier":"s:7OpenUSD3pxra","text":"pxr","kind":"typeIdentifier"},{"text":".","kind":"text"},{"preciseIdentifier":"c:@N@pxr@S@UsdLuxDomeLight_1","text":"UsdLuxDomeLight_1","kind":"typeIdentifier"},{"text":")","kind":"text"}]},"doc://SwiftUsd/documentation/OpenUSD/Swift/Bool/init(_:)-3bmqq":{"title":"init(_:)","fragments":[{"text":"init","kind":"identifier"},{"text":"(","kind":"text"},{"preciseIdentifier":"s:7OpenUSD3pxra","text":"pxr","kind":"typeIdentifier"},{"text":".","kind":"text"},{"preciseIdentifier":"c:@N@pxr@S@UsdLuxVolumeLightAPI","text":"UsdLuxVolumeLightAPI","kind":"typeIdentifier"},{"text":")","kind":"text"}],"role":"symbol","kind":"symbol","abstract":[],"type":"topic","identifier":"doc:\/\/SwiftUsd\/documentation\/OpenUSD\/Swift\/Bool\/init(_:)-3bmqq","url":"\/documentation\/openusd\/swift\/bool\/init(_:)-3bmqq"},"doc://SwiftUsd/documentation/OpenUSD/Swift/Bool/init(_:)-1vcgr":{"title":"init(_:)","identifier":"doc:\/\/SwiftUsd\/documentation\/OpenUSD\/Swift\/Bool\/init(_:)-1vcgr","type":"topic","fragments":[{"text":"init","kind":"identifier"},{"text":"(","kind":"text"},{"preciseIdentifier":"s:7OpenUSD3pxra","text":"pxr","kind":"typeIdentifier"},{"text":".","kind":"text"},{"preciseIdentifier":"c:@N@pxr@S@UsdLuxGeometryLight","text":"UsdLuxGeometryLight","kind":"typeIdentifier"},{"text":")","kind":"text"}],"url":"\/documentation\/openusd\/swift\/bool\/init(_:)-1vcgr","abstract":[],"role":"symbol","kind":"symbol"},"doc://SwiftUsd/documentation/OpenUSD/Swift/Bool/init(_:)-7z9sl":{"identifier":"doc:\/\/SwiftUsd\/documentation\/OpenUSD\/Swift\/Bool\/init(_:)-7z9sl","role":"symbol","abstract":[],"type":"topic","title":"init(_:)","kind":"symbol","fragments":[{"text":"init","kind":"identifier"},{"text":"(","kind":"text"},{"preciseIdentifier":"s:7OpenUSD3pxra","text":"pxr","kind":"typeIdentifier"},{"text":".","kind":"text"},{"preciseIdentifier":"c:@N@pxr@S@UsdRenderVar","text":"UsdRenderVar","kind":"typeIdentifier"},{"text":")","kind":"text"}],"url":"\/documentation\/openusd\/swift\/bool\/init(_:)-7z9sl"},"doc://SwiftUsd/documentation/OpenUSD/Swift/Bool/init(_:)-15ljn":{"title":"init(_:)","fragments":[{"text":"init","kind":"identifier"},{"text":"(","kind":"text"},{"preciseIdentifier":"s:7OpenUSD3pxra","text":"pxr","kind":"typeIdentifier"},{"text":".","kind":"text"},{"preciseIdentifier":"c:@N@pxr@S@UsdLuxLightFilter","text":"UsdLuxLightFilter","kind":"typeIdentifier"},{"text":")","kind":"text"}],"kind":"symbol","identifier":"doc:\/\/SwiftUsd\/documentation\/OpenUSD\/Swift\/Bool\/init(_:)-15ljn","abstract":[],"role":"symbol","url":"\/documentation\/openusd\/swift\/bool\/init(_:)-15ljn","type":"topic"},"doc://SwiftUsd/documentation/OpenUSD/Swift/Bool/init(_:)-57oub":{"type":"topic","url":"\/documentation\/openusd\/swift\/bool\/init(_:)-57oub","title":"init(_:)","role":"symbol","identifier":"doc:\/\/SwiftUsd\/documentation\/OpenUSD\/Swift\/Bool\/init(_:)-57oub","kind":"symbol","abstract":[],"fragments":[{"text":"init","kind":"identifier"},{"text":"(","kind":"text"},{"preciseIdentifier":"s:7OpenUSD3pxra","text":"pxr","kind":"typeIdentifier"},{"text":".","kind":"text"},{"preciseIdentifier":"c:@N@pxr@S@UsdUINodeGraphNodeAPI","text":"UsdUINodeGraphNodeAPI","kind":"typeIdentifier"},{"text":")","kind":"text"}]},"doc://SwiftUsd/documentation/OpenUSD/Swift/Bool/init(_:)-39ozz":{"title":"init(_:)","fragments":[{"text":"init","kind":"identifier"},{"text":"(","kind":"text"},{"preciseIdentifier":"s:7OpenUSD3pxra","text":"pxr","kind":"typeIdentifier"},{"text":".","kind":"text"},{"preciseIdentifier":"c:@N@pxr@S@UsdPhysicsJoint","text":"UsdPhysicsJoint","kind":"typeIdentifier"},{"text":")","kind":"text"}],"kind":"symbol","abstract":[],"url":"\/documentation\/openusd\/swift\/bool\/init(_:)-39ozz","type":"topic","role":"symbol","identifier":"doc:\/\/SwiftUsd\/documentation\/OpenUSD\/Swift\/Bool\/init(_:)-39ozz"},"doc://SwiftUsd/documentation/OpenUSD/Swift/Bool/init(_:)-1i5gv":{"abstract":[],"role":"symbol","url":"\/documentation\/openusd\/swift\/bool\/init(_:)-1i5gv","title":"init(_:)","fragments":[{"text":"init","kind":"identifier"},{"text":"(","kind":"text"},{"preciseIdentifier":"s:7OpenUSD3pxra","text":"pxr","kind":"typeIdentifier"},{"text":".","kind":"text"},{"preciseIdentifier":"c:@N@pxr@S@UsdGeomBoundable","text":"UsdGeomBoundable","kind":"typeIdentifier"},{"text":")","kind":"text"}],"identifier":"doc:\/\/SwiftUsd\/documentation\/OpenUSD\/Swift\/Bool\/init(_:)-1i5gv","type":"topic","kind":"symbol"},"doc://SwiftUsd/documentation/OpenUSD/Swift/Bool/init(_:)-92jm":{"url":"\/documentation\/openusd\/swift\/bool\/init(_:)-92jm","abstract":[],"fragments":[{"text":"init","kind":"identifier"},{"text":"(","kind":"text"},{"preciseIdentifier":"s:7OpenUSD3pxra","text":"pxr","kind":"typeIdentifier"},{"text":".","kind":"text"},{"preciseIdentifier":"c:@N@pxr@S@UsdSchemaBase","text":"UsdSchemaBase","kind":"typeIdentifier"},{"text":")","kind":"text"}],"type":"topic","kind":"symbol","role":"symbol","title":"init(_:)","identifier":"doc:\/\/SwiftUsd\/documentation\/OpenUSD\/Swift\/Bool\/init(_:)-92jm"},"doc://SwiftUsd/documentation/OpenUSD/Swift/Bool/init(_:)-5rhln":{"identifier":"doc:\/\/SwiftUsd\/documentation\/OpenUSD\/Swift\/Bool\/init(_:)-5rhln","title":"init(_:)","kind":"symbol","role":"symbol","abstract":[],"fragments":[{"text":"init","kind":"identifier"},{"text":"(","kind":"text"},{"preciseIdentifier":"s:7OpenUSD3pxra","text":"pxr","kind":"typeIdentifier"},{"text":".","kind":"text"},{"preciseIdentifier":"c:@N@pxr@S@UsdRiSplineAPI","text":"UsdRiSplineAPI","kind":"typeIdentifier"},{"text":")","kind":"text"}],"type":"topic","url":"\/documentation\/openusd\/swift\/bool\/init(_:)-5rhln"},"doc://SwiftUsd/documentation/OpenUSD/Swift/Bool/init(_:)-5ob92":{"title":"init(_:)","identifier":"doc:\/\/SwiftUsd\/documentation\/OpenUSD\/Swift\/Bool\/init(_:)-5ob92","abstract":[],"url":"\/documentation\/openusd\/swift\/bool\/init(_:)-5ob92","type":"topic","fragments":[{"text":"init","kind":"identifier"},{"text":"(","kind":"text"},{"preciseIdentifier":"s:7OpenUSD3pxra","text":"pxr","kind":"typeIdentifier"},{"text":".","kind":"text"},{"preciseIdentifier":"c:@N@pxr@S@UsdRenderPass","text":"UsdRenderPass","kind":"typeIdentifier"},{"text":")","kind":"text"}],"kind":"symbol","role":"symbol"},"doc://SwiftUsd/documentation/OpenUSD/Swift/Bool/init(_:)-54qbf":{"role":"symbol","fragments":[{"text":"init","kind":"identifier"},{"text":"(","kind":"text"},{"preciseIdentifier":"s:7OpenUSD3pxra","text":"pxr","kind":"typeIdentifier"},{"text":".","kind":"text"},{"preciseIdentifier":"c:@N@pxr@S@UsdPhysicsFixedJoint","text":"UsdPhysicsFixedJoint","kind":"typeIdentifier"},{"text":")","kind":"text"}],"title":"init(_:)","identifier":"doc:\/\/SwiftUsd\/documentation\/OpenUSD\/Swift\/Bool\/init(_:)-54qbf","abstract":[],"url":"\/documentation\/openusd\/swift\/bool\/init(_:)-54qbf","type":"topic","kind":"symbol"},"doc://SwiftUsd/documentation/OpenUSD/Swift/Bool/init(_:)-8ppxf":{"fragments":[{"text":"init","kind":"identifier"},{"text":"(","kind":"text"},{"preciseIdentifier":"s:7OpenUSD3pxra","text":"pxr","kind":"typeIdentifier"},{"text":".","kind":"text"},{"preciseIdentifier":"c:@N@pxr@S@UsdShadeNodeGraph","text":"UsdShadeNodeGraph","kind":"typeIdentifier"},{"text":")","kind":"text"}],"abstract":[],"title":"init(_:)","url":"\/documentation\/openusd\/swift\/bool\/init(_:)-8ppxf","type":"topic","role":"symbol","kind":"symbol","identifier":"doc:\/\/SwiftUsd\/documentation\/OpenUSD\/Swift\/Bool\/init(_:)-8ppxf"},"doc://SwiftUsd/documentation/OpenUSD/Swift/Bool":{"abstract":[],"identifier":"doc:\/\/SwiftUsd\/documentation\/OpenUSD\/Swift\/Bool","kind":"symbol","url":"\/documentation\/openusd\/swift\/bool","type":"topic","role":"symbol","title":"Bool","fragments":[{"kind":"keyword","text":"extension"},{"kind":"text","text":" "},{"kind":"identifier","preciseIdentifier":"s:Sb","text":"Bool"}],"navigatorTitle":[{"kind":"identifier","text":"Bool"}]},"doc://SwiftUsd/documentation/OpenUSD/Swift/Bool/init(_:)-1c4q4":{"identifier":"doc:\/\/SwiftUsd\/documentation\/OpenUSD\/Swift\/Bool\/init(_:)-1c4q4","type":"topic","url":"\/documentation\/openusd\/swift\/bool\/init(_:)-1c4q4","fragments":[{"text":"init","kind":"identifier"},{"text":"(","kind":"text"},{"preciseIdentifier":"s:7OpenUSD3pxra","text":"pxr","kind":"typeIdentifier"},{"text":".","kind":"text"},{"preciseIdentifier":"c:@N@pxr@S@UsdShadeConnectableAPI","text":"UsdShadeConnectableAPI","kind":"typeIdentifier"},{"text":")","kind":"text"}],"kind":"symbol","role":"symbol","title":"init(_:)","abstract":[]},"doc://SwiftUsd/documentation/OpenUSD/Swift/Bool/init(_:)-7wks3":{"url":"\/documentation\/openusd\/swift\/bool\/init(_:)-7wks3","type":"topic","identifier":"doc:\/\/SwiftUsd\/documentation\/OpenUSD\/Swift\/Bool\/init(_:)-7wks3","title":"init(_:)","abstract":[],"role":"symbol","kind":"symbol","fragments":[{"text":"init","kind":"identifier"},{"text":"(","kind":"text"},{"preciseIdentifier":"s:7OpenUSD3pxra","text":"pxr","kind":"typeIdentifier"},{"text":".","kind":"text"},{"preciseIdentifier":"c:@N@pxr@S@UsdLuxLightListAPI","text":"UsdLuxLightListAPI","kind":"typeIdentifier"},{"text":")","kind":"text"}]},"doc://SwiftUsd/documentation/OpenUSD/Swift/Bool/init(_:)-7ed54":{"title":"init(_:)","identifier":"doc:\/\/SwiftUsd\/documentation\/OpenUSD\/Swift\/Bool\/init(_:)-7ed54","abstract":[],"kind":"symbol","fragments":[{"kind":"identifier","text":"init"},{"kind":"text","text":"("},{"preciseIdentifier":"s:7OpenUSD3pxra","kind":"typeIdentifier","text":"pxr"},{"kind":"text","text":"."},{"preciseIdentifier":"c:@N@pxr@S@UsdLuxDomeLight","kind":"typeIdentifier","text":"UsdLuxDomeLight"},{"kind":"text","text":")"}],"role":"symbol","type":"topic","url":"\/documentation\/openusd\/swift\/bool\/init(_:)-7ed54"},"doc://SwiftUsd/documentation/OpenUSD/Swift/Bool/init(_:)-28oyy":{"role":"symbol","kind":"symbol","type":"topic","url":"\/documentation\/openusd\/swift\/bool\/init(_:)-28oyy","fragments":[{"text":"init","kind":"identifier"},{"text":"(","kind":"text"},{"preciseIdentifier":"s:7OpenUSD3pxra","text":"pxr","kind":"typeIdentifier"},{"text":".","kind":"text"},{"preciseIdentifier":"c:@N@pxr@S@UsdVolVolume","text":"UsdVolVolume","kind":"typeIdentifier"},{"text":")","kind":"text"}],"title":"init(_:)","abstract":[],"identifier":"doc:\/\/SwiftUsd\/documentation\/OpenUSD\/Swift\/Bool\/init(_:)-28oyy"},"doc://SwiftUsd/documentation/OpenUSD/Swift/Bool/init(_:)-47y4f":{"role":"symbol","abstract":[],"fragments":[{"text":"init","kind":"identifier"},{"text":"(","kind":"text"},{"preciseIdentifier":"s:7OpenUSD3pxra","text":"pxr","kind":"typeIdentifier"},{"text":".","kind":"text"},{"preciseIdentifier":"c:@N@pxr@S@UsdLuxPluginLightFilter","text":"UsdLuxPluginLightFilter","kind":"typeIdentifier"},{"text":")","kind":"text"}],"url":"\/documentation\/openusd\/swift\/bool\/init(_:)-47y4f","type":"topic","title":"init(_:)","identifier":"doc:\/\/SwiftUsd\/documentation\/OpenUSD\/Swift\/Bool\/init(_:)-47y4f","kind":"symbol"},"doc://SwiftUsd/documentation/OpenUSD/Swift/Bool/init(_:)-8vd8m":{"abstract":[],"title":"init(_:)","url":"\/documentation\/openusd\/swift\/bool\/init(_:)-8vd8m","type":"topic","fragments":[{"kind":"identifier","text":"init"},{"kind":"text","text":"("},{"kind":"typeIdentifier","preciseIdentifier":"s:7OpenUSD3pxra","text":"pxr"},{"kind":"text","text":"."},{"kind":"typeIdentifier","preciseIdentifier":"c:@N@pxr@S@UsdGeomNurbsPatch","text":"UsdGeomNurbsPatch"},{"kind":"text","text":")"}],"identifier":"doc:\/\/SwiftUsd\/documentation\/OpenUSD\/Swift\/Bool\/init(_:)-8vd8m","kind":"symbol","role":"symbol"},"doc://SwiftUsd/documentation/OpenUSD/Swift/Bool/init(_:)-2npd1":{"type":"topic","url":"\/documentation\/openusd\/swift\/bool\/init(_:)-2npd1","fragments":[{"text":"init","kind":"identifier"},{"text":"(","kind":"text"},{"preciseIdentifier":"s:7OpenUSD3pxra","text":"pxr","kind":"typeIdentifier"},{"text":".","kind":"text"},{"preciseIdentifier":"c:@N@pxr@S@UsdGeomMesh","text":"UsdGeomMesh","kind":"typeIdentifier"},{"text":")","kind":"text"}],"abstract":[],"identifier":"doc:\/\/SwiftUsd\/documentation\/OpenUSD\/Swift\/Bool\/init(_:)-2npd1","title":"init(_:)","role":"symbol","kind":"symbol"},"doc://SwiftUsd/documentation/OpenUSD/Swift/Bool/init(_:)-7gy5c":{"url":"\/documentation\/openusd\/swift\/bool\/init(_:)-7gy5c","title":"init(_:)","kind":"symbol","abstract":[],"identifier":"doc:\/\/SwiftUsd\/documentation\/OpenUSD\/Swift\/Bool\/init(_:)-7gy5c","fragments":[{"text":"init","kind":"identifier"},{"text":"(","kind":"text"},{"preciseIdentifier":"s:7OpenUSD3pxra","text":"pxr","kind":"typeIdentifier"},{"text":".","kind":"text"},{"preciseIdentifier":"c:@N@pxr@S@UsdRiMaterialAPI","text":"UsdRiMaterialAPI","kind":"typeIdentifier"},{"text":")","kind":"text"}],"role":"symbol","type":"topic"},"doc://SwiftUsd/documentation/OpenUSD/Swift/Bool/init(_:)-2azq4":{"title":"init(_:)","abstract":[],"identifier":"doc:\/\/SwiftUsd\/documentation\/OpenUSD\/Swift\/Bool\/init(_:)-2azq4","type":"topic","role":"symbol","url":"\/documentation\/openusd\/swift\/bool\/init(_:)-2azq4","fragments":[{"text":"init","kind":"identifier"},{"text":"(","kind":"text"},{"preciseIdentifier":"s:7OpenUSD3pxra","text":"pxr","kind":"typeIdentifier"},{"text":".","kind":"text"},{"preciseIdentifier":"c:@N@pxr@S@UsdGeomCylinder_1","text":"UsdGeomCylinder_1","kind":"typeIdentifier"},{"text":")","kind":"text"}],"kind":"symbol"},"doc://SwiftUsd/documentation/OpenUSD/Swift/Bool/init(_:)-97fah":{"fragments":[{"text":"init","kind":"identifier"},{"text":"(","kind":"text"},{"preciseIdentifier":"s:7OpenUSD3pxra","text":"pxr","kind":"typeIdentifier"},{"text":".","kind":"text"},{"preciseIdentifier":"c:@N@pxr@S@UsdTyped","text":"UsdTyped","kind":"typeIdentifier"},{"text":")","kind":"text"}],"type":"topic","role":"symbol","title":"init(_:)","abstract":[],"url":"\/documentation\/openusd\/swift\/bool\/init(_:)-97fah","identifier":"doc:\/\/SwiftUsd\/documentation\/OpenUSD\/Swift\/Bool\/init(_:)-97fah","kind":"symbol"},"doc://SwiftUsd/documentation/OpenUSD/Swift/Bool/init(_:)-9w25":{"kind":"symbol","title":"init(_:)","type":"topic","fragments":[{"text":"init","kind":"identifier"},{"text":"(","kind":"text"},{"preciseIdentifier":"s:7OpenUSD3pxra","text":"pxr","kind":"typeIdentifier"},{"text":".","kind":"text"},{"preciseIdentifier":"c:@N@pxr@S@UsdVolFieldAsset","text":"UsdVolFieldAsset","kind":"typeIdentifier"},{"text":")","kind":"text"}],"url":"\/documentation\/openusd\/swift\/bool\/init(_:)-9w25","role":"symbol","identifier":"doc:\/\/SwiftUsd\/documentation\/OpenUSD\/Swift\/Bool\/init(_:)-9w25","abstract":[]},"doc://SwiftUsd/documentation/OpenUSD/Swift/Bool/init(_:)-9s4hm":{"abstract":[],"role":"symbol","identifier":"doc:\/\/SwiftUsd\/documentation\/OpenUSD\/Swift\/Bool\/init(_:)-9s4hm","fragments":[{"text":"init","kind":"identifier"},{"text":"(","kind":"text"},{"preciseIdentifier":"s:7OpenUSD3pxra","text":"pxr","kind":"typeIdentifier"},{"text":".","kind":"text"},{"preciseIdentifier":"c:@N@pxr@S@UsdGeomScope","text":"UsdGeomScope","kind":"typeIdentifier"},{"text":")","kind":"text"}],"kind":"symbol","title":"init(_:)","type":"topic","url":"\/documentation\/openusd\/swift\/bool\/init(_:)-9s4hm"},"doc://SwiftUsd/documentation/OpenUSD/Swift/Bool/init(_:)-jwh4":{"url":"\/documentation\/openusd\/swift\/bool\/init(_:)-jwh4","kind":"symbol","title":"init(_:)","type":"topic","abstract":[],"fragments":[{"text":"init","kind":"identifier"},{"text":"(","kind":"text"},{"preciseIdentifier":"s:7OpenUSD3pxra","text":"pxr","kind":"typeIdentifier"},{"text":".","kind":"text"},{"preciseIdentifier":"c:@N@pxr@S@UsdGeomPoints","text":"UsdGeomPoints","kind":"typeIdentifier"},{"text":")","kind":"text"}],"identifier":"doc:\/\/SwiftUsd\/documentation\/OpenUSD\/Swift\/Bool\/init(_:)-jwh4","role":"symbol"},"doc://SwiftUsd/documentation/OpenUSD/Swift/Bool/init(_:)-4bxp0":{"type":"topic","title":"init(_:)","url":"\/documentation\/openusd\/swift\/bool\/init(_:)-4bxp0","kind":"symbol","role":"symbol","fragments":[{"text":"init","kind":"identifier"},{"text":"(","kind":"text"},{"preciseIdentifier":"s:7OpenUSD3pxra","text":"pxr","kind":"typeIdentifier"},{"text":".","kind":"text"},{"preciseIdentifier":"c:@N@pxr@S@UsdPhysicsMaterialAPI","text":"UsdPhysicsMaterialAPI","kind":"typeIdentifier"},{"text":")","kind":"text"}],"abstract":[],"identifier":"doc:\/\/SwiftUsd\/documentation\/OpenUSD\/Swift\/Bool\/init(_:)-4bxp0"},"doc://SwiftUsd/documentation/OpenUSD/Swift/Bool/init(_:)-99xbt":{"kind":"symbol","identifier":"doc:\/\/SwiftUsd\/documentation\/OpenUSD\/Swift\/Bool\/init(_:)-99xbt","type":"topic","role":"symbol","url":"\/documentation\/openusd\/swift\/bool\/init(_:)-99xbt","fragments":[{"text":"init","kind":"identifier"},{"text":"(","kind":"text"},{"preciseIdentifier":"s:7OpenUSD3pxra","text":"pxr","kind":"typeIdentifier"},{"text":".","kind":"text"},{"preciseIdentifier":"c:@N@pxr@S@UsdColorSpaceAPI","text":"UsdColorSpaceAPI","kind":"typeIdentifier"},{"text":")","kind":"text"}],"abstract":[],"title":"init(_:)"},"doc://SwiftUsd/documentation/OpenUSD/Swift/Bool/init(_:)-8q0js":{"role":"symbol","title":"init(_:)","identifier":"doc:\/\/SwiftUsd\/documentation\/OpenUSD\/Swift\/Bool\/init(_:)-8q0js","abstract":[],"kind":"symbol","url":"\/documentation\/openusd\/swift\/bool\/init(_:)-8q0js","type":"topic","fragments":[{"text":"init","kind":"identifier"},{"text":"(","kind":"text"},{"preciseIdentifier":"s:7OpenUSD3pxra","text":"pxr","kind":"typeIdentifier"},{"text":".","kind":"text"},{"preciseIdentifier":"c:@N@pxr@S@UsdGeomImageable","text":"UsdGeomImageable","kind":"typeIdentifier"},{"text":")","kind":"text"}]},"doc://SwiftUsd/documentation/OpenUSD/Swift/Bool/init(_:)-3qdpt":{"fragments":[{"text":"init","kind":"identifier"},{"text":"(","kind":"text"},{"preciseIdentifier":"s:7OpenUSD3pxra","text":"pxr","kind":"typeIdentifier"},{"text":".","kind":"text"},{"preciseIdentifier":"c:@N@pxr@S@UsdColorSpaceDefinitionAPI","text":"UsdColorSpaceDefinitionAPI","kind":"typeIdentifier"},{"text":")","kind":"text"}],"type":"topic","kind":"symbol","title":"init(_:)","url":"\/documentation\/openusd\/swift\/bool\/init(_:)-3qdpt","abstract":[],"identifier":"doc:\/\/SwiftUsd\/documentation\/OpenUSD\/Swift\/Bool\/init(_:)-3qdpt","role":"symbol"},"doc://SwiftUsd/documentation/OpenUSD/Swift/Bool/init(_:)-2hek2":{"type":"topic","kind":"symbol","title":"init(_:)","identifier":"doc:\/\/SwiftUsd\/documentation\/OpenUSD\/Swift\/Bool\/init(_:)-2hek2","role":"symbol","url":"\/documentation\/openusd\/swift\/bool\/init(_:)-2hek2","fragments":[{"text":"init","kind":"identifier"},{"text":"(","kind":"text"},{"preciseIdentifier":"s:7OpenUSD3pxra","text":"pxr","kind":"typeIdentifier"},{"text":".","kind":"text"},{"preciseIdentifier":"c:@N@pxr@S@UsdPhysicsRigidBodyAPI","text":"UsdPhysicsRigidBodyAPI","kind":"typeIdentifier"},{"text":")","kind":"text"}],"abstract":[]},"doc://SwiftUsd/documentation/OpenUSD/Swift/Bool/init(_:)-7tyzt":{"fragments":[{"text":"init","kind":"identifier"},{"text":"(","kind":"text"},{"preciseIdentifier":"s:7OpenUSD3pxra","text":"pxr","kind":"typeIdentifier"},{"text":".","kind":"text"},{"preciseIdentifier":"c:@N@pxr@S@UsdRenderSettingsBase","text":"UsdRenderSettingsBase","kind":"typeIdentifier"},{"text":")","kind":"text"}],"type":"topic","url":"\/documentation\/openusd\/swift\/bool\/init(_:)-7tyzt","title":"init(_:)","role":"symbol","kind":"symbol","abstract":[],"identifier":"doc:\/\/SwiftUsd\/documentation\/OpenUSD\/Swift\/Bool\/init(_:)-7tyzt"},"doc://SwiftUsd/documentation/OpenUSD/Swift/Bool/init(_:)-6qnkg":{"abstract":[],"url":"\/documentation\/openusd\/swift\/bool\/init(_:)-6qnkg","kind":"symbol","title":"init(_:)","identifier":"doc:\/\/SwiftUsd\/documentation\/OpenUSD\/Swift\/Bool\/init(_:)-6qnkg","type":"topic","fragments":[{"text":"init","kind":"identifier"},{"text":"(","kind":"text"},{"preciseIdentifier":"s:7OpenUSD3pxra","text":"pxr","kind":"typeIdentifier"},{"text":".","kind":"text"},{"preciseIdentifier":"c:@N@pxr@S@UsdPhysicsCollisionAPI","text":"UsdPhysicsCollisionAPI","kind":"typeIdentifier"},{"text":")","kind":"text"}],"role":"symbol"},"doc://SwiftUsd/documentation/OpenUSD/Swift/Bool/init(_:)-1mmhr":{"abstract":[],"identifier":"doc:\/\/SwiftUsd\/documentation\/OpenUSD\/Swift\/Bool\/init(_:)-1mmhr","url":"\/documentation\/openusd\/swift\/bool\/init(_:)-1mmhr","fragments":[{"text":"init","kind":"identifier"},{"text":"(","kind":"text"},{"preciseIdentifier":"s:7OpenUSD3pxra","text":"pxr","kind":"typeIdentifier"},{"text":".","kind":"text"},{"preciseIdentifier":"c:@N@pxr@S@UsdLuxLightAPI","text":"UsdLuxLightAPI","kind":"typeIdentifier"},{"text":")","kind":"text"}],"title":"init(_:)","kind":"symbol","type":"topic","role":"symbol"},"doc://SwiftUsd/documentation/OpenUSD/Swift/Bool/init(_:)-40c5m":{"kind":"symbol","role":"symbol","title":"init(_:)","identifier":"doc:\/\/SwiftUsd\/documentation\/OpenUSD\/Swift\/Bool\/init(_:)-40c5m","abstract":[],"fragments":[{"text":"init","kind":"identifier"},{"text":"(","kind":"text"},{"preciseIdentifier":"s:7OpenUSD3pxra","text":"pxr","kind":"typeIdentifier"},{"text":".","kind":"text"},{"preciseIdentifier":"c:@N@pxr@S@UsdGeomVisibilityAPI","text":"UsdGeomVisibilityAPI","kind":"typeIdentifier"},{"text":")","kind":"text"}],"type":"topic","url":"\/documentation\/openusd\/swift\/bool\/init(_:)-40c5m"},"doc://SwiftUsd/documentation/OpenUSD/Swift/Bool/init(_:)-4mfl7":{"title":"init(_:)","kind":"symbol","abstract":[],"fragments":[{"text":"init","kind":"identifier"},{"text":"(","kind":"text"},{"preciseIdentifier":"s:7OpenUSD3pxra","text":"pxr","kind":"typeIdentifier"},{"text":".","kind":"text"},{"preciseIdentifier":"c:@N@pxr@S@UsdVolField3DAsset","text":"UsdVolField3DAsset","kind":"typeIdentifier"},{"text":")","kind":"text"}],"url":"\/documentation\/openusd\/swift\/bool\/init(_:)-4mfl7","type":"topic","identifier":"doc:\/\/SwiftUsd\/documentation\/OpenUSD\/Swift\/Bool\/init(_:)-4mfl7","role":"symbol"},"doc://SwiftUsd/documentation/OpenUSD/Swift/Bool/init(_:)-4a2cx":{"abstract":[],"title":"init(_:)","identifier":"doc:\/\/SwiftUsd\/documentation\/OpenUSD\/Swift\/Bool\/init(_:)-4a2cx","kind":"symbol","fragments":[{"text":"init","kind":"identifier"},{"text":"(","kind":"text"},{"preciseIdentifier":"s:7OpenUSD3pxra","text":"pxr","kind":"typeIdentifier"},{"text":".","kind":"text"},{"preciseIdentifier":"c:@N@pxr@S@UsdShadeMaterialBindingAPI","text":"UsdShadeMaterialBindingAPI","kind":"typeIdentifier"},{"text":")","kind":"text"}],"type":"topic","url":"\/documentation\/openusd\/swift\/bool\/init(_:)-4a2cx","role":"symbol"},"doc://SwiftUsd/documentation/OpenUSD/Swift/Bool/init(_:)-3t2wb":{"type":"topic","fragments":[{"text":"init","kind":"identifier"},{"text":"(","kind":"text"},{"preciseIdentifier":"s:7OpenUSD3pxra","text":"pxr","kind":"typeIdentifier"},{"text":".","kind":"text"},{"preciseIdentifier":"c:@N@pxr@S@UsdGeomSubset","text":"UsdGeomSubset","kind":"typeIdentifier"},{"text":")","kind":"text"}],"url":"\/documentation\/openusd\/swift\/bool\/init(_:)-3t2wb","identifier":"doc:\/\/SwiftUsd\/documentation\/OpenUSD\/Swift\/Bool\/init(_:)-3t2wb","title":"init(_:)","role":"symbol","kind":"symbol","abstract":[]},"doc://SwiftUsd/documentation/OpenUSD/Swift/Bool/init(_:)-5jboq":{"abstract":[],"title":"init(_:)","fragments":[{"text":"init","kind":"identifier"},{"text":"(","kind":"text"},{"preciseIdentifier":"s:7OpenUSD3pxra","text":"pxr","kind":"typeIdentifier"},{"text":".","kind":"text"},{"preciseIdentifier":"c:@N@pxr@S@UsdMediaAssetPreviewsAPI","text":"UsdMediaAssetPreviewsAPI","kind":"typeIdentifier"},{"text":")","kind":"text"}],"identifier":"doc:\/\/SwiftUsd\/documentation\/OpenUSD\/Swift\/Bool\/init(_:)-5jboq","type":"topic","url":"\/documentation\/openusd\/swift\/bool\/init(_:)-5jboq","role":"symbol","kind":"symbol"},"doc://SwiftUsd/documentation/OpenUSD/Swift/Bool/init(_:)-1tb4n":{"title":"init(_:)","role":"symbol","kind":"symbol","identifier":"doc:\/\/SwiftUsd\/documentation\/OpenUSD\/Swift\/Bool\/init(_:)-1tb4n","abstract":[{"type":"text","text":"Returns "},{"code":"true","type":"codeVoice"},{"type":"text","text":" if the "},{"code":"HioImage","type":"codeVoice"},{"type":"text","text":" is valid"}],"fragments":[{"text":"init","kind":"identifier"},{"text":"(","kind":"text"},{"preciseIdentifier":"c:@N@Overlay","text":"Overlay","kind":"typeIdentifier"},{"text":".","kind":"text"},{"preciseIdentifier":"c:@N@Overlay@S@HioImageWrapper","text":"HioImageWrapper","kind":"typeIdentifier"},{"text":")","kind":"text"}],"url":"\/documentation\/openusd\/swift\/bool\/init(_:)-1tb4n","type":"topic"},"doc://SwiftUsd/documentation/OpenUSD/Swift/Bool/init(_:)-qbsh":{"title":"init(_:)","role":"symbol","type":"topic","fragments":[{"text":"init","kind":"identifier"},{"text":"(","kind":"text"},{"preciseIdentifier":"s:7OpenUSD3pxra","text":"pxr","kind":"typeIdentifier"},{"text":".","kind":"text"},{"preciseIdentifier":"c:@N@pxr@S@UsdPhysicsDriveAPI","text":"UsdPhysicsDriveAPI","kind":"typeIdentifier"},{"text":")","kind":"text"}],"abstract":[],"kind":"symbol","url":"\/documentation\/openusd\/swift\/bool\/init(_:)-qbsh","identifier":"doc:\/\/SwiftUsd\/documentation\/OpenUSD\/Swift\/Bool\/init(_:)-qbsh"},"doc://SwiftUsd/documentation/OpenUSD/Swift/Bool/init(_:)-2ganp":{"identifier":"doc:\/\/SwiftUsd\/documentation\/OpenUSD\/Swift\/Bool\/init(_:)-2ganp","fragments":[{"text":"init","kind":"identifier"},{"text":"(","kind":"text"},{"preciseIdentifier":"s:7OpenUSD3pxra","text":"pxr","kind":"typeIdentifier"},{"text":".","kind":"text"},{"preciseIdentifier":"c:@N@pxr@S@UsdGeomXformOp","text":"UsdGeomXformOp","kind":"typeIdentifier"},{"text":")","kind":"text"}],"role":"symbol","title":"init(_:)","url":"\/documentation\/openusd\/swift\/bool\/init(_:)-2ganp","kind":"symbol","abstract":[{"type":"text","text":"Returns "},{"code":"true","type":"codeVoice"},{"type":"text","text":" if the "},{"code":"UsdGeomXformOp","type":"codeVoice"},{"type":"text","text":" is valid"}],"type":"topic"}}}